[
    {
        "place_id": "ChIJWf_vWdMWAhMRe_ikkH0B0vQ",
        "name": "Copa Cabana",
        "description": null,
        "is_spending_on_ads": false,
        "reviews": 53,
        "website": null,
        "owner": {
            "id": null,
            "name": "Copa Cabana (proprietaire)",
            "link": null
        },
        "featured_image": "https://lh5.googleusercontent.com/p/AF1QipPfrhZFBKC6RZdpFgoH0U9VJJ2yHl8xiknhLRnm=w408-h306-k-no",
        "main_category": "Restaurant",
        "categories": [
            "Restaurant"
        ],
        "rating": 4.1,
        "workday_timing": "11:00-23:00",
        "closed_on": [],
        "phone": "50 530 430",
        "address": "JVVR+HCC Copa Cabana, Ksar Hellal",
        "review_keywords": [
            {
                "keyword": "pizza",
                "count": 4
            },
            {
                "keyword": "tacos",
                "count": 3
            }
        ],
        "link": "https://www.google.com/maps/place/Copa+Cabana/data=!4m7!3m6!1s0x130216d359efff59:0xf4d2017d90a4f87b!8m2!3d35.6439406!4d10.8910213!16s%2Fg%2F11fz9xx44z!19sChIJWf_vWdMWAhMRe_ikkH0B0vQ?authuser=0&hl=fr&rclk=1"
    },
    {
        "place_id": "ChIJAQAAACQRAhMRdcosavj1VIQ",
        "name": "Restaurant Ezzarda",
        "description": null,
        "is_spending_on_ads": false,
        "reviews": 27,
        "website": null,
        "owner": {
            "id": null,
            "name": "Restaurant Ezzarda (proprietaire)",
            "link": null
        },
        "featured_image": "https://lh5.googleusercontent.com/p/AF1QipN9B9cGxxTZB2wrGnuu1vmbMVNMzzeVX5kKNmyn=w408-h545-k-no",
        "main_category": "Restaurant",
        "categories": [
            "Restaurant"
        ],
        "rating": 4.4,
        "workday_timing": "10:00-22:00",
        "closed_on": [],
        "phone": "97 890 766",
        "address": "MV3Q+8QH Restaurant Ezzarda, Ksar Hellal",
        "review_keywords": [],
        "link": "https://www.google.com/maps/place/Restaurant+Ezzarda/data=!4m7!3m6!1s0x1302112400000001:0x8454f5f86a2cca75!8m2!3d35.6532575!4d10.8894799!16s%2Fg%2F11c0pvfmpw!19sChIJAQAAACQRAhMRdcosavj1VIQ?authuser=0&hl=fr&rclk=1"
    },
    {
        "place_id": "ChIJDe_dzcoWAhMR5KkZ5JgZmG8",
        "name": "Cafe de l'Excellence",
        "description": null,
        "is_spending_on_ads": false,
        "reviews": 24,
        "website": null,
        "owner": {
            "id": null,
            "name": "Cafe de l'Excellence (proprietaire)",
            "link": null
        },
        "featured_image": "https://lh5.googleusercontent.com/p/AF1QipPJbO5WOMeuY1gRY5ikvEjHGfia0UjXLK2yxqQi=w408-h544-k-no",
        "main_category": "Cafe",
        "categories": [
            "Cafe"
        ],
        "rating": 4.5,
        "workday_timing": "Ouvert 24h/24",
        "closed_on": [],
        "phone": null,
        "address": "MV5R+67F Cafe de l'Excellence, Av. Habib Bourguiba, Ksar Hellal",
        "review_keywords": [],
        "link": "https://www.google.com/maps/place/Caf%C3%A9+de+l%27Excellence/data=!4m7!3m6!1s0x130216cacdddef0d:0x6f981998e419a9e4!8m2!3d35.6580503!4d10.8906627!16s%2Fg%2F11b6wghy32!19sChIJDe_dzcoWAhMR5KkZ5JgZmG8?authuser=0&hl=fr&rclk=1"
    },
    {
        "place_id": "ChIJJ_Xy0FkRAhMRTGnJ4JLD0r8",
        "name": "Chaneb Food shnb fwd",
        "description": null,
        "is_spending_on_ads": false,
        "reviews": 22,
        "website": null,
        "owner": {
            "id": "104422441157294540395",
            "name": "Chaneb Food shnb fwd (proprietaire)",
            "link": "https://www.google.com/maps/contrib/104422441157294540395"
        },
        "featured_image": "https://lh5.googleusercontent.com/p/AF1QipNnyfgAhE0llHyXiagZ_Nrs4niKVEldmIEh4m-X=w408-h306-k-no",
        "main_category": "Restauration rapide",
        "categories": [
            "Restauration rapide",
            "Restaurant tunisien"
        ],
        "rating": 4.4,
        "workday_timing": "11:00-23:00",
        "closed_on": [],
        "phone": "58 336 336",
        "address": "Chaneb Food shnb fwd, En Face De << ZEN >>, 199 Av. Habib bourguiba, Ksar Hellal 5070",
        "review_keywords": [],
        "link": "https://www.google.com/maps/place/Chaneb+Food+%D8%B4%D9%86%D8%A7%D8%A8+%D9%81%D9%88%D8%AF%E2%80%AD/data=!4m7!3m6!1s0x13021159d0f2f527:0xbfd2c392e0c9694c!8m2!3d35.648245!4d10.8846906!16s%2Fg%2F11qnt8fkxg!19sChIJJ_Xy0FkRAhMRTGnJ4JLD0r8?authuser=0&hl=fr&rclk=1"
    },
    {
        "place_id": "ChIJrfK8kDARAhMR_0E0F-R93To",
        "name": "Restaurant Al Moulouk",
        "description": null,
        "is_spending_on_ads": false,
        "reviews": 18,
        "website": null,
        "owner": {
            "id": null,
            "name": "Restaurant Al Moulouk (proprietaire)",
            "link": null
        },
        "featured_image": "https://lh5.googleusercontent.com/p/AF1QipMKb744b6J_o_GAR1ty3S-KLKXnTaNlMBW0EEKM=w408-h544-k-no",
        "main_category": "Restaurant",
        "categories": [
            "Restaurant"
        ],
        "rating": 4,
        "workday_timing": "09:00-22:00",
        "closed_on": [],
        "phone": "27 024 405",
        "address": "MV3H+FWG Restaurant Al Moulouk, Av. Habib bourguiba, Ksar Hellal",
        "review_keywords": [],
        "link": "https://www.google.com/maps/place/Restaurant+Al+Moulouk/data=!4m7!3m6!1s0x1302113090bcf2ad:0x3add7de4173441ff!8m2!3d35.6536851!4d10.8798155!16s%2Fg%2F11gb3pr7g2!19sChIJrfK8kDARAhMR_0E0F-R93To?authuser=0&hl=fr&rclk=1"
    },
    {
        "place_id": "ChIJK8HzBqYRAhMRwobN5RDLtxI",
        "name": "Papa Grill",
        "description": null,
        "is_spending_on_ads": false,
        "reviews": 18,
        "website": null,
        "owner": {
            "id": "102028663611789146327",
            "name": "Papa Grill (proprietaire)",
            "link": "https://www.google.com/maps/contrib/102028663611789146327"
        },
        "featured_image": "https://lh5.googleusercontent.com/p/AF1QipNVtDQqdNC7-QhMbxG9lZoOMGjsc_EKlO4DC2c0=w408-h291-k-no",
        "main_category": "Restaurant de grillades",
        "categories": [
            "Restaurant de grillades"
        ],
        "rating": 4,
        "workday_timing": null,
        "closed_on": [],
        "phone": "53 045 045",
        "address": "Papa Grill, Av. Hadj Ali Soua, Ksar Hellal",
        "review_keywords": [
            {
                "keyword": "cuite",
                "count": 3
            }
        ],
        "link": "https://www.google.com/maps/place/Papa+Grill/data=!4m7!3m6!1s0x130211a606f3c12b:0x12b7cb10e5cd86c2!8m2!3d35.6546785!4d10.8902283!16s%2Fg%2F11krrcshdm!19sChIJK8HzBqYRAhMRwobN5RDLtxI?authuser=0&hl=fr&rclk=1"
    },
    {
        "place_id": "ChIJF-rxT9MWAhMR-WX_To026xA",
        "name": "Volcano",
        "description": null,
        "is_spending_on_ads": false,
        "reviews": 14,
        "website": null,
        "owner": {
            "id": null,
            "name": "Volcano (proprietaire)",
            "link": null
        },
        "featured_image": "https://lh5.googleusercontent.com/p/AF1QipOkbwj7yiUD4zPuQkNOHCUsN1dBOMvDwONWgpj7=w426-h240-k-no",
        "main_category": "Restaurant",
        "categories": [
            "Restaurant"
        ],
        "rating": 4.4,
        "workday_timing": "13:00-00:00",
        "closed_on": [
            "dimanche"
        ],
        "phone": "98 288 755",
        "address": "JVVR+Q95 Volcano, Ksar Hellal",
        "review_keywords": [],
        "link": "https://www.google.com/maps/place/Volcano/data=!4m7!3m6!1s0x130216d34ff1ea17:0x10eb368d4eff65f9!8m2!3d35.6443919!4d10.8909759!16s%2Fg%2F11bz_yczyc!19sChIJF-rxT9MWAhMR-WX_To026xA?authuser=0&hl=fr&rclk=1"
    },
    {
        "place_id": "ChIJUzPfWXQXAhMRMFDOp3C1bJ0",
        "name": "SULTANE EL CHAM",
        "description": null,
        "is_spending_on_ads": false,
        "reviews": 11,
        "website": null,
        "owner": {
            "id": null,
            "name": "SULTANE EL CHAM (proprietaire)",
            "link": null
        },
        "featured_image": "https://lh5.googleusercontent.com/p/AF1QipPsnmr42igtJimrnxP6A8E8zVXIXxwdwWHgES3b=w533-h240-k-no",
        "main_category": "Pizzeria",
        "categories": [
            "Pizzeria"
        ],
        "rating": 4.4,
        "workday_timing": "08:00-23:00",
        "closed_on": [
            "lundi"
        ],
        "phone": "95 911 911",
        "address": "JVWR+PGW SULTANE EL CHAM, Av. Habib Bourguiba, Ksar Hellal",
        "review_keywords": [],
        "link": "https://www.google.com/maps/place/SULTANE+EL+CHAM/data=!4m7!3m6!1s0x1302177459df3353:0x9d6cb570a7ce5030!8m2!3d35.6467824!4d10.8913317!16s%2Fg%2F11rclk8xjd!19sChIJUzPfWXQXAhMRMFDOp3C1bJ0?authuser=0&hl=fr&rclk=1"
    },
    {
        "place_id": "ChIJlXQR3n0XAhMRLEWXzufvEzM",
        "name": "Target Pizza",
        "description": null,
        "is_spending_on_ads": false,
        "reviews": 10,
        "website": null,
        "owner": {
            "id": null,
            "name": "Target Pizza (proprietaire)",
            "link": null
        },
        "featured_image": "https://lh5.googleusercontent.com/p/AF1QipOkcarHaWyMzrqklgHQvfx9FfGOcqk1AbFsOEDi=w408-h272-k-no",
        "main_category": "Pizzeria",
        "categories": [
            "Pizzeria"
        ],
        "rating": 4.8,
        "workday_timing": null,
        "closed_on": [],
        "phone": "73 587 760",
        "address": "MV5R+396 Target Pizza, Av. Habib Bourguiba, Ksar Hellal 5070",
        "review_keywords": [],
        "link": "https://www.google.com/maps/place/Target+Pizza/data=!4m7!3m6!1s0x1302177dde117495:0x3313efe7ce97452c!8m2!3d35.657659!4d10.8908926!16s%2Fg%2F11nnzgmvp7!19sChIJlXQR3n0XAhMRLEWXzufvEzM?authuser=0&hl=fr&rclk=1"
    },
    {
        "place_id": "ChIJIZ9ngfoRAhMRiGv6ToXi240",
        "name": "Cafe Hugo Said",
        "description": null,
        "is_spending_on_ads": false,
        "reviews": 10,
        "website": null,
        "owner": {
            "id": null,
            "name": "Cafe Hugo Said (proprietaire)",
            "link": null
        },
        "featured_image": "https://lh5.googleusercontent.com/p/AF1QipMbADRaKjZ-qOaPwShKdvkEptG5k2fQ7apdWd7o=w408-h306-k-no",
        "main_category": "Cafe",
        "categories": [
            "Cafe",
            "Restaurant"
        ],
        "rating": 4.3,
        "workday_timing": "Ouvert 24h/24",
        "closed_on": [],
        "phone": null,
        "address": "MV3Q+7Q4 Cafe Hugo Said, Ksar Hellal",
        "review_keywords": [],
        "link": "https://www.google.com/maps/place/Caf%C3%A9+Hugo+Sa%C3%AFd/data=!4m7!3m6!1s0x130211fa81679f21:0x8ddbe2854efa6b88!8m2!3d35.6531383!4d10.8894671!16s%2Fg%2F11pz51wx06!19sChIJIZ9ngfoRAhMRiGv6ToXi240?authuser=0&hl=fr&rclk=1"
    },
    {
        "place_id": "ChIJHQwGK6QRAhMR_UKEBZeGh-A",
        "name": "Jus becha",
        "description": null,
        "is_spending_on_ads": false,
        "reviews": 6,
        "website": null,
        "owner": {
            "id": null,
            "name": "Jus becha (proprietaire)",
            "link": null
        },
        "featured_image": "https://lh5.googleusercontent.com/p/AF1QipNs_w7Pi0CI-kc0J8mF7UrKM7JU4MWwvIiobK_5=w408-h306-k-no",
        "main_category": "Restaurant",
        "categories": [
            "Restaurant"
        ],
        "rating": 5,
        "workday_timing": "08:30-20:00",
        "closed_on": [],
        "phone": "20 500 223",
        "address": "MV2P+3RJ Jus becha, Av. Des Nations Unis, Ksar Hellal",
        "review_keywords": [],
        "link": "https://www.google.com/maps/place/Jus+becha/data=!4m7!3m6!1s0x130211a42b060c1d:0xe0878697058442fd!8m2!3d35.6502217!4d10.8870245!16s%2Fg%2F11fkvnmf7x!19sChIJHQwGK6QRAhMR_UKEBZeGh-A?authuser=0&hl=fr&rclk=1"
    },
    {
        "place_id": "ChIJbaj37ywRAhMR2rQ0mCOUM-4",
        "name": "Restaurant flefel flyfl",
        "description": null,
        "is_spending_on_ads": false,
        "reviews": 6,
        "website": null,
        "owner": {
            "id": null,
            "name": "Restaurant flefel flyfl (proprietaire)",
            "link": null
        },
        "featured_image": null,
        "main_category": "Restaurant",
        "categories": [
            "Restaurant"
        ],
        "rating": 4.5,
        "workday_timing": "10:00-22:30",
        "closed_on": [],
        "phone": null,
        "address": "JVWQ+97P Restaurant flefel flyfl, Ksar Hellal",
        "review_keywords": [],
        "link": "https://www.google.com/maps/place/Restaurant+flefel+%D9%81%D9%84%D9%8A%D9%81%D9%84%E2%80%AD/data=!4m7!3m6!1s0x1302112ceff7a86d:0xee3394239834b4da!8m2!3d35.6459746!4d10.8881876!16s%2Fg%2F11dztlh8nw!19sChIJbaj37ywRAhMR2rQ0mCOUM-4?authuser=0&hl=fr&rclk=1"
    },
    {
        "place_id": "ChIJ-5Rm_ggXAhMRVJMys13clIw",
        "name": "BAM COFFEE SHOP",
        "description": null,
        "is_spending_on_ads": false,
        "reviews": 6,
        "website": null,
        "owner": {
            "id": null,
            "name": "BAM COFFEE SHOP (proprietaire)",
            "link": null
        },
        "featured_image": "https://streetviewpixels-pa.googleapis.com/v1/thumbnail?panoid=7AnBpBOKch3slvMuYV0jig&cb_client=search.gws-prod.gps&w=408&h=240&yaw=51.90749&pitch=0&thumbfov=100",
        "main_category": "Cafe",
        "categories": [
            "Cafe"
        ],
        "rating": 4.5,
        "workday_timing": "Ouvert 24h/24",
        "closed_on": [],
        "phone": "52 334 344",
        "address": "MV4R+Q82 BAM COFFEE SHOP, Av. Habib Bourguiba, Ksar Hellal",
        "review_keywords": [],
        "link": "https://www.google.com/maps/place/BAM+COFFEE+SHOP/data=!4m7!3m6!1s0x13021708fe6694fb:0x8c94dc5db3329354!8m2!3d35.6568918!4d10.8907778!16s%2Fg%2F11r3tgfgkq!19sChIJ-5Rm_ggXAhMRVJMys13clIw?authuser=0&hl=fr&rclk=1"
    },
    {
        "place_id": "ChIJtwA8zzIRAhMRvPyUOb81wWQ",
        "name": "Dar ZMEN",
        "description": null,
        "is_spending_on_ads": false,
        "reviews": 5,
        "website": null,
        "owner": {
            "id": null,
            "name": "Dar ZMEN (proprietaire)",
            "link": null
        },
        "featured_image": "https://lh5.googleusercontent.com/p/AF1QipNG4FVr480eFduwpz68M3b2aWsRZSAQvCwjAvA0=w408-h907-k-no",
        "main_category": "Restaurant",
        "categories": [
            "Restaurant"
        ],
        "rating": 4.8,
        "workday_timing": "10:00-17:00",
        "closed_on": [],
        "phone": "52 216 933",
        "address": "JVVR+M88 Dar ZMEN, Av. Habib Bourguiba, Ksar Hellal",
        "review_keywords": [],
        "link": "https://www.google.com/maps/place/Dar+ZMEN/data=!4m7!3m6!1s0x13021132cf3c00b7:0x64c135bf3994fcbc!8m2!3d35.6441675!4d10.8908286!16s%2Fg%2F11g69xk8r3!19sChIJtwA8zzIRAhMRvPyUOb81wWQ?authuser=0&hl=fr&rclk=1"
    },
    {
        "place_id": "ChIJvdNQIvUXAhMR3Lodmsfb624",
        "name": "Soltane Elchem",
        "description": null,
        "is_spending_on_ads": false,
        "reviews": 3,
        "website": null,
        "owner": {
            "id": null,
            "name": "Soltane Elchem (proprietaire)",
            "link": null
        },
        "featured_image": "https://lh5.googleusercontent.com/p/AF1QipPAW7CO-I3aHzav50eIGcb2XsGtxOL78PEbYVZ9=w426-h240-k-no",
        "main_category": "Restaurant familial",
        "categories": [
            "Restaurant familial"
        ],
        "rating": 4.3,
        "workday_timing": "09:00-23:30",
        "closed_on": [],
        "phone": null,
        "address": "JVWR+PGW Soltane Elchem, Av. Habib Bourguiba, Ksar Hellal",
        "review_keywords": [],
        "link": "https://www.google.com/maps/place/Soltane+Elchem/data=!4m7!3m6!1s0x130217f52250d3bd:0x6eebdbc79a1dbadc!8m2!3d35.6467808!4d10.8913384!16s%2Fg%2F11l1js4q11!19sChIJvdNQIvUXAhMR3Lodmsfb624?authuser=0&hl=fr&rclk=1"
    },
    {
        "place_id": "ChIJi3gh2zcXAhMRzjXCJI1BFB4",
        "name": "Twins + Coffee",
        "description": null,
        "is_spending_on_ads": false,
        "reviews": 3,
        "website": null,
        "owner": {
            "id": "102852720001467763124",
            "name": "Twins + Coffee (proprietaire)",
            "link": "https://www.google.com/maps/contrib/102852720001467763124"
        },
        "featured_image": "https://lh5.googleusercontent.com/p/AF1QipNNRfZGN9mC_4zM1HhFjiE1gPd57odUQHHe6YoQ=w408-h724-k-no",
        "main_category": "Cafe",
        "categories": [
            "Cafe"
        ],
        "rating": 5,
        "workday_timing": "06:30-22:30",
        "closed_on": [],
        "phone": "24 145 614",
        "address": "Twins + Coffee, 5070",
        "review_keywords": [],
        "link": "https://www.google.com/maps/place/Twins+%2B+Coffee/data=!4m7!3m6!1s0x13021737db21788b:0x1e14418d24c235ce!8m2!3d35.6493707!4d10.8924156!16s%2Fg%2F11jm9ns5l2!19sChIJi3gh2zcXAhMRzjXCJI1BFB4?authuser=0&hl=fr&rclk=1"
    },
    {
        "place_id": "ChIJ2wD8RdMWAhMRIICIMt18g14",
        "name": "Cafe Elyssa",
        "description": null,
        "is_spending_on_ads": false,
        "reviews": 3,
        "website": null,
        "owner": {
            "id": "106530777176885662917",
            "name": "Cafe Elyssa (proprietaire)",
            "link": "https://www.google.com/maps/contrib/106530777176885662917"
        },
        "featured_image": "https://lh5.googleusercontent.com/p/AF1QipMPTE7KE0bv-4X6v2JFGC71TKZwPV5A6XrEB30v=w428-h240-k-no",
        "main_category": "Cafe",
        "categories": [
            "Cafe"
        ],
        "rating": 5,
        "workday_timing": "05:00-00:00",
        "closed_on": [],
        "phone": "55 111 108",
        "address": "Cafe Elyssa, Av. Habib bourguiba, Ksar Hellal 5070",
        "review_keywords": [],
        "link": "https://www.google.com/maps/place/Cafe+Elyssa/data=!4m7!3m6!1s0x130216d345fc00db:0x5e837cdd32888020!8m2!3d35.6445502!4d10.8909605!16s%2Fg%2F11c5bhl_7j!19sChIJ2wD8RdMWAhMRIICIMt18g14?authuser=0&hl=fr&rclk=1"
    },
    {
        "place_id": "ChIJEfQqxTERAhMR9pA9lIQQq8w",
        "name": "patisserie confiserie marocaine",
        "description": null,
        "is_spending_on_ads": false,
        "reviews": 3,
        "website": null,
        "owner": {
            "id": null,
            "name": "patisserie confiserie marocaine (proprietaire)",
            "link": null
        },
        "featured_image": "https://streetviewpixels-pa.googleapis.com/v1/thumbnail?panoid=PgGQhjV6hci0KFvSdDOPlg&cb_client=search.gws-prod.gps&w=408&h=240&yaw=202.45&pitch=0&thumbfov=100",
        "main_category": "Restaurant",
        "categories": [
            "Restaurant"
        ],
        "rating": 4.3,
        "workday_timing": "07:00-19:00",
        "closed_on": [],
        "phone": "98 208 908",
        "address": "MV2M+53W patisserie confiserie marocaine, Ksar Hellal",
        "review_keywords": [],
        "link": "https://www.google.com/maps/place/patisserie+confiserie+marocaine/data=!4m7!3m6!1s0x13021131c52af411:0xccab1084943d90f6!8m2!3d35.6504966!4d10.8827157!16s%2Fg%2F11cpfw171g!19sChIJEfQqxTERAhMR9pA9lIQQq8w?authuser=0&hl=fr&rclk=1"
    },
    {
        "place_id": "ChIJtdJ-BTsRAhMRT9l_qxz3mC8",
        "name": "Dreams food",
        "description": null,
        "is_spending_on_ads": false,
        "reviews": 2,
        "website": null,
        "owner": {
            "id": null,
            "name": "Dreams food (proprietaire)",
            "link": null
        },
        "featured_image": "https://lh5.googleusercontent.com/p/AF1QipO8l9voE_LIgNd7hjOukWa7CBVcjUmVw6FmXhHq=w426-h240-k-no",
        "main_category": "Restaurant",
        "categories": [
            "Restaurant"
        ],
        "rating": 5,
        "workday_timing": null,
        "closed_on": [],
        "phone": "52 844 006",
        "address": "JVVQ+WJF Dreams food, station taxi, Ksar Hellal",
        "review_keywords": [],
        "link": "https://www.google.com/maps/place/Dreams+food/data=!4m7!3m6!1s0x1302113b057ed2b5:0x2f98f71cab7fd94f!8m2!3d35.6448057!4d10.8890365!16s%2Fg%2F11gxvscw0v!19sChIJtdJ-BTsRAhMRT9l_qxz3mC8?authuser=0&hl=fr&rclk=1"
    },
    {
        "place_id": "ChIJxaUS71UXAhMR-klfiscga9g",
        "name": "OMEK TANGO - 'mWk Tnqw",
        "description": null,
        "is_spending_on_ads": false,
        "reviews": 2,
        "website": null,
        "owner": {
            "id": "116600706771912430024",
            "name": "OMEK TANGO - 'mWk Tnqw (proprietaire)",
            "link": "https://www.google.com/maps/contrib/116600706771912430024"
        },
        "featured_image": "https://lh5.googleusercontent.com/p/AF1QipOZxyNEBgLCcXAktNf8Q5Pm_FNSyoJ55lcy6yP6=w408-h612-k-no",
        "main_category": "Restaurant",
        "categories": [
            "Restaurant"
        ],
        "rating": 5,
        "workday_timing": "10:00-18:00",
        "closed_on": [
            "lundi"
        ],
        "phone": null,
        "address": "OMEK TANGO - 'mWk Tnqw, Av. Hadj Ali Soua, Ksar Hellal 5070",
        "review_keywords": [],
        "link": "https://www.google.com/maps/place/OMEK+TANGO+-+%D8%A3%D9%85%D9%91%D9%83+%D8%B7%D9%86%D9%82%D9%88%E2%80%AD/data=!4m7!3m6!1s0x13021755ef12a5c5:0xd86b20c78a5f49fa!8m2!3d35.6580046!4d10.8911318!16s%2Fg%2F11vsph8c1c!19sChIJxaUS71UXAhMR-klfiscga9g?authuser=0&hl=fr&rclk=1"
    },
    {
        "place_id": "ChIJ_QLUMaURAhMRbDB1QW9RkFU",
        "name": "Willy's Food",
        "description": null,
        "is_spending_on_ads": false,
        "reviews": 1,
        "website": null,
        "owner": {
            "id": null,
            "name": "Willy's Food (proprietaire)",
            "link": null
        },
        "featured_image": null,
        "main_category": "Restaurant",
        "categories": [
            "Restaurant"
        ],
        "rating": 5,
        "workday_timing": "Ouvert 24h/24",
        "closed_on": [],
        "phone": "53 673 995",
        "address": "JVRQ+R6W Willy's Food, Rue al-rebat, Ksar Hellal 5070",
        "review_keywords": [],
        "link": "https://www.google.com/maps/place/Willy%E2%80%99s+Food/data=!4m7!3m6!1s0x130211a531d402fd:0x5590516f4175306c!8m2!3d35.6421108!4d10.8880715!16s%2Fg%2F11rj44r0m5!19sChIJ_QLUMaURAhMRbDB1QW9RkFU?authuser=0&hl=fr&rclk=1"
    },
    {
        "place_id": "ChIJuX6MdhcRAhMReuUpzWIIzag",
        "name": "ALADIN PASTRY",
        "description": null,
        "is_spending_on_ads": false,
        "reviews": 1,
        "website": null,
        "owner": {
            "id": null,
            "name": "ALADIN PASTRY (proprietaire)",
            "link": null
        },
        "featured_image": "https://lh5.googleusercontent.com/p/AF1QipNrH_q0GzH2VD0tObE1STBVaTgmrpEAbs9JJzBP=w426-h240-k-no",
        "main_category": "Restaurant",
        "categories": [
            "Restaurant"
        ],
        "rating": 5,
        "workday_timing": "07:30-23:00",
        "closed_on": [],
        "phone": "53 590 809",
        "address": "MV27+WVR ALADIN PASTRY, Unnamed Road, Ksar Hellal",
        "review_keywords": [],
        "link": "https://www.google.com/maps/place/ALADIN+PASTRY/data=!4m7!3m6!1s0x13021117768c7eb9:0xa8cd0862cd29e57a!8m2!3d35.6523606!4d10.8646298!16s%2Fg%2F11hc_m3wvg!19sChIJuX6MdhcRAhMReuUpzWIIzag?authuser=0&hl=fr&rclk=1"
    },
    {
        "place_id": "ChIJd7jR4wERAhMRDY_TbyYuSkw",
        "name": "Fast food coba",
        "description": null,
        "is_spending_on_ads": false,
        "reviews": 1,
        "website": null,
        "owner": {
            "id": null,
            "name": "Fast food coba (proprietaire)",
            "link": null
        },
        "featured_image": null,
        "main_category": "Restaurant",
        "categories": [
            "Restaurant"
        ],
        "rating": 5,
        "workday_timing": null,
        "closed_on": [],
        "phone": "50 530 430",
        "address": "JVWF+485 Fast food coba, Ksar Hellal",
        "review_keywords": [],
        "link": "https://www.google.com/maps/place/Fast+food+coba/data=!4m7!3m6!1s0x13021101e3d1b877:0x4c4a2e266fd38f0d!8m2!3d35.6452612!4d10.8733712!16s%2Fg%2F11h77_h0dl!19sChIJd7jR4wERAhMRDY_TbyYuSkw?authuser=0&hl=fr&rclk=1"
    },
    {
        "place_id": "ChIJwzcFHycRAhMRicXaJ_6wuhI",
        "name": "Ayoub hamami",
        "description": null,
        "is_spending_on_ads": false,
        "reviews": 1,
        "website": null,
        "owner": {
            "id": "111950760873049503110",
            "name": "Ayoub hamami (proprietaire)",
            "link": "https://www.google.com/maps/contrib/111950760873049503110"
        },
        "featured_image": "https://lh5.googleusercontent.com/p/AF1QipO89hGThwBcJoblS628Arcjw5y_8i8MZmAHIaFq=w408-h680-k-no",
        "main_category": "Restaurant",
        "categories": [
            "Restaurant"
        ],
        "rating": 5,
        "workday_timing": "21:06-09:06",
        "closed_on": [
            "lundi",
            "mardi",
            "mercredi",
            "vendredi",
            "samedi",
            "dimanche"
        ],
        "phone": "94 968 219",
        "address": "Ayoub hamami, Unnamed Road, Ksar Hellal",
        "review_keywords": [],
        "link": "https://www.google.com/maps/place/Ayoub+hamami/data=!4m7!3m6!1s0x130211271f0537c3:0x12bab0fe27dac589!8m2!3d35.642182!4d10.8749352!16s%2Fg%2F11fyzbsgzn!19sChIJwzcFHycRAhMRicXaJ_6wuhI?authuser=0&hl=fr&rclk=1"
    },
    {
        "place_id": "ChIJQxkKbCURAhMReo3mR6Myqzc",
        "name": "Chapati La Cabana",
        "description": null,
        "is_spending_on_ads": false,
        "reviews": 1,
        "website": null,
        "owner": {
            "id": null,
            "name": "Chapati La Cabana (proprietaire)",
            "link": null
        },
        "featured_image": "https://streetviewpixels-pa.googleapis.com/v1/thumbnail?panoid=yfGpcOmp76ArCO3Wcjc1ZA&cb_client=search.gws-prod.gps&w=408&h=240&yaw=262.3848&pitch=0&thumbfov=100",
        "main_category": "Restauration rapide",
        "categories": [
            "Restauration rapide"
        ],
        "rating": 5,
        "workday_timing": null,
        "closed_on": [],
        "phone": null,
        "address": "MV2Q+WM6 Chapati La Cabana, Av. Habib Bourguiba, Ksar Hellal",
        "review_keywords": [],
        "link": "https://www.google.com/maps/place/Chapati+La+Cabana/data=!4m7!3m6!1s0x130211256c0a1943:0x37ab32a347e68d7a!8m2!3d35.6522828!4d10.8891435!16s%2Fg%2F11h7fxx756!19sChIJQxkKbCURAhMReo3mR6Myqzc?authuser=0&hl=fr&rclk=1"
    },
    {
        "place_id": "ChIJk-KIa84RAhMR58gDEiMyREE",
        "name": "Billionaire cafe",
        "description": null,
        "is_spending_on_ads": false,
        "reviews": 1,
        "website": null,
        "owner": {
            "id": null,
            "name": "Billionaire cafe (proprietaire)",
            "link": null
        },
        "featured_image": "https://lh5.googleusercontent.com/p/AF1QipO2FIZOyB34Jo8aamjQcOafwvrCBGjZeRl4ivbH=w408-h296-k-no",
        "main_category": "Cafe",
        "categories": [
            "Cafe"
        ],
        "rating": 4,
        "workday_timing": null,
        "closed_on": [],
        "phone": null,
        "address": "MV4C+CG6 Billionaire cafe, Erriadh, Ksar Hellal",
        "review_keywords": [],
        "link": "https://www.google.com/maps/place/Billionaire+caf%C3%A9/data=!4m7!3m6!1s0x130211ce6b88e293:0x414432231203c8e7!8m2!3d35.6562268!4d10.8721902!16s%2Fg%2F11kjg9mqsf!19sChIJk-KIa84RAhMR58gDEiMyREE?authuser=0&hl=fr&rclk=1"
    },
    {
        "place_id": "ChIJ-RL3a28RAhMReb-UbAF6A5k",
        "name": "The Deal Sweet & Salty",
        "description": null,
        "is_spending_on_ads": false,
        "reviews": 1,
        "website": null,
        "owner": {
            "id": null,
            "name": "The Deal Sweet & Salty (proprietaire)",
            "link": null
        },
        "featured_image": "https://lh5.googleusercontent.com/p/AF1QipNkpqz6ecuNr81Gye5-BuU2dArL8uE95MW3Yqzm=w408-h510-k-no",
        "main_category": "Restauration rapide",
        "categories": [
            "Restauration rapide"
        ],
        "rating": 5,
        "workday_timing": null,
        "closed_on": [],
        "phone": "22 367 217",
        "address": "The Deal Sweet & Salty, 165-157 Av. Habib bourguiba, Ksar Hellal",
        "review_keywords": [],
        "link": "https://www.google.com/maps/place/The+Deal+Sweet+%26+Salty/data=!4m7!3m6!1s0x1302116f6bf712f9:0x99037a016c94bf79!8m2!3d35.6473278!4d10.8850651!16s%2Fg%2F11q8vzn62s!19sChIJ-RL3a28RAhMReb-UbAF6A5k?authuser=0&hl=fr&rclk=1"
    }
]