[
    {
        "place_id": "ChIJPXKWVI0j4xIRKD4BOvAnjvE",
        "name": "mozart",
        "description": null,
        "is_spending_on_ads": false,
        "reviews": 33,
        "website": null,
        "owner": {
            "id": "117826494194216585648",
            "name": "mozart (proprietaire)",
            "link": "https://www.google.com/maps/contrib/117826494194216585648"
        },
        "featured_image": "https://lh5.googleusercontent.com/p/AF1QipMxbNO_Maw3rvMPggKZZDxRe3mieBPmlu6c-gQ=w426-h240-k-no",
        "main_category": "Restaurant",
        "categories": [
            "Restaurant"
        ],
        "rating": 4.1,
        "workday_timing": "09:00-00:00",
        "closed_on": [],
        "phone": null,
        "address": "5Q5Q+JHX mozart, Ex. rue Colbert, Menzel Bourguiba",
        "review_keywords": [],
        "link": "https://www.google.com/maps/place/mozart/data=!4m7!3m6!1s0x12e3238d5496723d:0xf18e27f03a013e28!8m2!3d37.1584374!4d9.7899918!16s%2Fg%2F1yghd1cbm!19sChIJPXKWVI0j4xIRKD4BOvAnjvE?authuser=0&hl=fr&rclk=1"
    },
    {
        "place_id": "ChIJzbi03-Aj4xIRX-xeclb2RIc",
        "name": "Cafe Sidi Yahia",
        "description": null,
        "is_spending_on_ads": false,
        "reviews": 19,
        "website": null,
        "owner": {
            "id": null,
            "name": "Cafe Sidi Yahia (proprietaire)",
            "link": null
        },
        "featured_image": "https://lh5.googleusercontent.com/p/AF1QipMC-DHq8Et4LUbMKY2rqQ65MMDFYG3fdqVHYkLe=w408-h306-k-no",
        "main_category": "Cafe",
        "categories": [
            "Cafe"
        ],
        "rating": 4.3,
        "workday_timing": "06:00-23:00",
        "closed_on": [],
        "phone": "99 532 241",
        "address": "5Q7M+HFR Cafe Sidi Yahia, Unnamed Road, Menzel Bourguiba",
        "review_keywords": [],
        "link": "https://www.google.com/maps/place/Caf%C3%A9+Sidi+Yahia/data=!4m7!3m6!1s0x12e323e0dfb4b8cd:0x8744f656725eec5f!8m2!3d37.163979!4d9.7836299!16s%2Fg%2F11h1m585rs!19sChIJzbi03-Aj4xIRX-xeclb2RIc?authuser=0&hl=fr&rclk=1"
    },
    {
        "place_id": "ChIJ9dBz-_Ej4xIRI_zvdmFMTdc",
        "name": "Cafe de Nice",
        "description": null,
        "is_spending_on_ads": false,
        "reviews": 16,
        "website": null,
        "owner": {
            "id": null,
            "name": "Cafe de Nice (proprietaire)",
            "link": null
        },
        "featured_image": "https://lh5.googleusercontent.com/p/AF1QipMxInPIaN3Q5nQSO46ZiO4etcJoB8_-14eg_3fi=w426-h240-k-no",
        "main_category": "Cafe",
        "categories": [
            "Cafe"
        ],
        "rating": 4.3,
        "workday_timing": "06:30-23:00",
        "closed_on": [],
        "phone": null,
        "address": "5Q5W+4G7 Cafe de Nice, Av. de Palestine, Manzil Bu Ruqaybah",
        "review_keywords": [],
        "link": "https://www.google.com/maps/place/Caf%C3%A9+de+Nice/data=!4m7!3m6!1s0x12e323f1fb73d0f5:0xd74d4c6176effc23!8m2!3d37.1577984!4d9.7962923!16s%2Fg%2F1td6jkr2!19sChIJ9dBz-_Ej4xIRI_zvdmFMTdc?authuser=0&hl=fr&rclk=1"
    },
    {
        "place_id": "ChIJqRU9vZcj4xIRX3EReRriDbw",
        "name": "Taco's",
        "description": null,
        "is_spending_on_ads": false,
        "reviews": 15,
        "website": null,
        "owner": {
            "id": "113213232939081573933",
            "name": "Taco's (proprietaire)",
            "link": "https://www.google.com/maps/contrib/113213232939081573933"
        },
        "featured_image": "https://lh5.googleusercontent.com/p/AF1QipN9qPuY1On61SLWowC3YM55Oy_WD4vrVtOLrmso=w408-h408-k-no",
        "main_category": "Restaurant de tacos",
        "categories": [
            "Restaurant de tacos",
            "Creperie",
            "Restaurant de desserts"
        ],
        "rating": 4.5,
        "workday_timing": "11:00-21:30",
        "closed_on": [
            "mardi"
        ],
        "phone": "90 314 227",
        "address": "Taco's, Av. de L'independance, Menzel Bourguiba 7050",
        "review_keywords": [],
        "link": "https://www.google.com/maps/place/Taco%27s/data=!4m7!3m6!1s0x12e32397bd3d15a9:0xbc0de21a7911715f!8m2!3d37.1567525!4d9.7858567!16s%2Fg%2F11nn2v0_0q!19sChIJqRU9vZcj4xIRX3EReRriDbw?authuser=0&hl=fr&rclk=1"
    },
    {
        "place_id": "ChIJVXZoE_Qj4xIR1z0AThU1aFk",
        "name": "Cafe Flamenco",
        "description": null,
        "is_spending_on_ads": false,
        "reviews": 12,
        "website": null,
        "owner": {
            "id": null,
            "name": "Cafe Flamenco (proprietaire)",
            "link": null
        },
        "featured_image": "https://streetviewpixels-pa.googleapis.com/v1/thumbnail?panoid=SirNITNT4_R9jFa9gbN1Cg&cb_client=search.gws-prod.gps&w=408&h=240&yaw=193.16072&pitch=0&thumbfov=100",
        "main_category": "Cafe",
        "categories": [
            "Cafe"
        ],
        "rating": 4,
        "workday_timing": "06:00-00:00",
        "closed_on": [],
        "phone": null,
        "address": "5Q2V+RQP Cafe Flamenco, Menzel Bourguiba",
        "review_keywords": [],
        "link": "https://www.google.com/maps/place/Caf%C3%A9+Flamenco/data=!4m7!3m6!1s0x12e323f413687655:0x596835154e003dd7!8m2!3d37.1520808!4d9.7944581!16s%2Fg%2F11g_d3m3d!19sChIJVXZoE_Qj4xIR1z0AThU1aFk?authuser=0&hl=fr&rclk=1"
    },
    {
        "place_id": "ChIJI3qrRo4j4xIRY3d9RhggF9A",
        "name": "Cafe la Sirene",
        "description": null,
        "is_spending_on_ads": false,
        "reviews": 8,
        "website": null,
        "owner": {
            "id": null,
            "name": "Cafe la Sirene (proprietaire)",
            "link": null
        },
        "featured_image": "https://streetviewpixels-pa.googleapis.com/v1/thumbnail?panoid=8j1GGe1wEgNKmiOtCpme8w&cb_client=search.gws-prod.gps&w=408&h=240&yaw=34.97193&pitch=0&thumbfov=100",
        "main_category": "Cafe",
        "categories": [
            "Cafe"
        ],
        "rating": 4.6,
        "workday_timing": null,
        "closed_on": [],
        "phone": null,
        "address": "5Q5M+34P Cafe la Sirene, Av. de L'independance, Menzel Bourguiba",
        "review_keywords": [],
        "link": "https://www.google.com/maps/place/Caf%C3%A9+la+Sir%C3%A9ne/data=!4m7!3m6!1s0x12e3238e46ab7a23:0xd0172018467d7763!8m2!3d37.157708!4d9.7828259!16s%2Fg%2F1hf418fwz!19sChIJI3qrRo4j4xIRY3d9RhggF9A?authuser=0&hl=fr&rclk=1"
    },
    {
        "place_id": "ChIJi0UwtYoj4xIRc3w8TlLLIZU",
        "name": "Cafe ben Fattoum",
        "description": null,
        "is_spending_on_ads": false,
        "reviews": 7,
        "website": null,
        "owner": {
            "id": null,
            "name": "Cafe ben Fattoum (proprietaire)",
            "link": null
        },
        "featured_image": "https://lh5.googleusercontent.com/p/AF1QipNYYEnvFIkGHsm5szCkWbS8pPM1aOHrmvt042JW=w408-h259-k-no",
        "main_category": "Cafe",
        "categories": [
            "Cafe"
        ],
        "rating": 4.3,
        "workday_timing": "Ouvert 24h/24",
        "closed_on": [],
        "phone": null,
        "address": "4QXR+P36 Cafe ben Fattoum, Menzel Bourguiba",
        "review_keywords": [],
        "link": "https://www.google.com/maps/place/Cafe+ben+Fattoum/data=!4m7!3m6!1s0x12e3238ab530458b:0x9521cb524e3c7c73!8m2!3d37.1492962!4d9.7901427!16s%2Fg%2F11gfnjbr0q!19sChIJi0UwtYoj4xIRc3w8TlLLIZU?authuser=0&hl=fr&rclk=1"
    },
    {
        "place_id": "ChIJVY0zX6Ij4xIReLRDzJeKTyk",
        "name": "HolyMoly Restaurant",
        "description": null,
        "is_spending_on_ads": false,
        "reviews": 7,
        "website": null,
        "owner": {
            "id": "107710582262385714914",
            "name": "HolyMoly Restaurant (proprietaire)",
            "link": "https://www.google.com/maps/contrib/107710582262385714914"
        },
        "featured_image": "https://lh5.googleusercontent.com/p/AF1QipMez_ncurhB-MSOsUniURn9WF6JWj4I7B6xOy3u=w408-h305-k-no",
        "main_category": "Restauration rapide",
        "categories": [
            "Restauration rapide"
        ],
        "rating": 4.4,
        "workday_timing": "Ouvert 24h/24",
        "closed_on": [],
        "phone": "25 123 580",
        "address": "HolyMoly Restaurant, Menzel Bourguiba",
        "review_keywords": [],
        "link": "https://www.google.com/maps/place/HolyMoly+Restaurant/data=!4m7!3m6!1s0x12e323a25f338d55:0x294f8a97cc43b478!8m2!3d37.1526925!4d9.791291!16s%2Fg%2F11rl2hbc1f!19sChIJVY0zX6Ij4xIReLRDzJeKTyk?authuser=0&hl=fr&rclk=1"
    },
    {
        "place_id": "ChIJs2pQ648j4xIR-ZmMAMztC5U",
        "name": "Cafe Ben Mahmoud",
        "description": null,
        "is_spending_on_ads": false,
        "reviews": 6,
        "website": null,
        "owner": {
            "id": null,
            "name": "Cafe Ben Mahmoud (proprietaire)",
            "link": null
        },
        "featured_image": "https://lh5.googleusercontent.com/p/AF1QipNLyQXqt-as6Fmvmh7xTu9SMwVpVKEMSDfTHwj7=w408-h544-k-no",
        "main_category": "Cafe",
        "categories": [
            "Cafe"
        ],
        "rating": 4.5,
        "workday_timing": "04:30-23:30",
        "closed_on": [],
        "phone": null,
        "address": "5Q5J+72W Cafe Ben Mahmoud, Av. de L'independance, Menzel Bourguiba",
        "review_keywords": [],
        "link": "https://www.google.com/maps/place/Caf%C3%A9+Ben+Mahmoud/data=!4m7!3m6!1s0x12e3238feb506ab3:0x950bedcc008c99f9!8m2!3d37.1582308!4d9.7800902!16s%2Fg%2F1hf1mfxq6!19sChIJs2pQ648j4xIR-ZmMAMztC5U?authuser=0&hl=fr&rclk=1"
    },
    {
        "place_id": "ChIJiyYH2_Qj4xIRDwDE2bOM6gc",
        "name": "Cafe Elmadina",
        "description": null,
        "is_spending_on_ads": false,
        "reviews": 6,
        "website": null,
        "owner": {
            "id": null,
            "name": "Cafe Elmadina (proprietaire)",
            "link": null
        },
        "featured_image": "https://lh5.googleusercontent.com/p/AF1QipN3vaHv0QrETNHU0yWb5mJAwhWbAGQ8Rl9dEsAD=w408-h725-k-no",
        "main_category": "Cafe",
        "categories": [
            "Cafe"
        ],
        "rating": 4,
        "workday_timing": "06:00-23:30",
        "closed_on": [],
        "phone": null,
        "address": "5Q2R+FC8 Cafe Elmadina, Menzel Bourguiba",
        "review_keywords": [],
        "link": "https://www.google.com/maps/place/Cafe+Elmadina/data=!4m7!3m6!1s0x12e323f4db07268b:0x7ea8cb3d9c4000f!8m2!3d37.1511725!4d9.7910643!16s%2Fg%2F11h9rpjd5l!19sChIJiyYH2_Qj4xIRDwDE2bOM6gc?authuser=0&hl=fr&rclk=1"
    },
    {
        "place_id": "ChIJwQ-Np-8j4xIRy9v1SCJpeHA",
        "name": "cafe iris",
        "description": null,
        "is_spending_on_ads": false,
        "reviews": 6,
        "website": null,
        "owner": {
            "id": null,
            "name": "cafe iris (proprietaire)",
            "link": null
        },
        "featured_image": "https://lh5.googleusercontent.com/p/AF1QipPammPKA4LTsfvuUNe7F9pKjjxeRnUtOf1S7B5V=w408-h544-k-no",
        "main_category": "Cafe",
        "categories": [
            "Cafe"
        ],
        "rating": 4,
        "workday_timing": "05:00-00:00",
        "closed_on": [],
        "phone": "22 827 702",
        "address": "5Q6X+6QJ cafe iris, Menzel Bourguiba",
        "review_keywords": [],
        "link": "https://www.google.com/maps/place/caf%C3%A9+iris/data=!4m7!3m6!1s0x12e323efa78d0fc1:0x7078692248f5dbcb!8m2!3d37.160586!4d9.7993792!16s%2Fg%2F11g8vcd4w6!19sChIJwQ-Np-8j4xIRy9v1SCJpeHA?authuser=0&hl=fr&rclk=1"
    },
    {
        "place_id": "ChIJj-LRx4Ij4xIRp8c1957cSeQ",
        "name": "cafe angolo d'or",
        "description": null,
        "is_spending_on_ads": false,
        "reviews": 6,
        "website": null,
        "owner": {
            "id": null,
            "name": "cafe angolo d'or (proprietaire)",
            "link": null
        },
        "featured_image": "https://lh5.googleusercontent.com/p/AF1QipPvd1qIuCFU_X1L7Y5Qwt_cc0uS8vcMJC2g_nIB=w408-h544-k-no",
        "main_category": "Cafe",
        "categories": [
            "Cafe"
        ],
        "rating": 4,
        "workday_timing": "04:00-00:00",
        "closed_on": [],
        "phone": "95 999 959",
        "address": "5Q59+VQJ cafe angolo d'or, Av. de L'independance, Menzel Bourguiba",
        "review_keywords": [],
        "link": "https://www.google.com/maps/place/caf%C3%A9+angolo+d%27or/data=!4m7!3m6!1s0x12e32382c7d1e28f:0xe449dc9ef735c7a7!8m2!3d37.159702!4d9.7693826!16s%2Fg%2F11bzwnmhvm!19sChIJj-LRx4Ij4xIRp8c1957cSeQ?authuser=0&hl=fr&rclk=1"
    },
    {
        "place_id": "ChIJL1CTBQAj4xIR_QURhaXtHqQ",
        "name": "fTyr bw`wn",
        "description": null,
        "is_spending_on_ads": false,
        "reviews": 6,
        "website": null,
        "owner": {
            "id": "111510413733394435936",
            "name": "fTyr bw`wn (proprietaire)",
            "link": "https://www.google.com/maps/contrib/111510413733394435936"
        },
        "featured_image": "https://lh5.googleusercontent.com/p/AF1QipMPjQdWYKL6va_phzA_wTakTFMcCXhaDHA8lPsK=w408-h306-k-no",
        "main_category": "Restaurant",
        "categories": [
            "Restaurant"
        ],
        "rating": 5,
        "workday_timing": null,
        "closed_on": [],
        "phone": null,
        "address": "fTyr bw`wn, rue de Corse, Menzel Bourguiba",
        "review_keywords": [],
        "link": "https://www.google.com/maps/place/%D9%81%D8%B7%D8%A7%D9%8A%D8%B1+%D8%A8%D9%88%D8%B9%D9%88%D9%86%E2%80%AD/data=!4m7!3m6!1s0x12e323000593502f:0xa41eeda5851105fd!8m2!3d37.1540595!4d9.7941231!16s%2Fg%2F11h52n0y8b!19sChIJL1CTBQAj4xIR_QURhaXtHqQ?authuser=0&hl=fr&rclk=1"
    },
    {
        "place_id": "ChIJS2yPrfMj4xIRNEQt1j9elQ0",
        "name": "Cafe Resto L'mama",
        "description": null,
        "is_spending_on_ads": false,
        "reviews": 5,
        "website": null,
        "owner": {
            "id": null,
            "name": "Cafe Resto L'mama (proprietaire)",
            "link": null
        },
        "featured_image": "https://streetviewpixels-pa.googleapis.com/v1/thumbnail?panoid=tUWzkd77AiltUU9dWkVftQ&cb_client=search.gws-prod.gps&w=408&h=240&yaw=286.19794&pitch=0&thumbfov=100",
        "main_category": "Restaurant",
        "categories": [
            "Restaurant"
        ],
        "rating": 4.8,
        "workday_timing": null,
        "closed_on": [],
        "phone": null,
        "address": "5Q4V+M63 Cafe Resto L'mama, rue de la republique, Menzel Bourguiba",
        "review_keywords": [],
        "link": "https://www.google.com/maps/place/Cafe+Resto+L%27mama/data=!4m7!3m6!1s0x12e323f3ad8f6c4b:0xd955e3fd62d4434!8m2!3d37.156631!4d9.7930339!16s%2Fg%2F11hd1qvmp3!19sChIJS2yPrfMj4xIRNEQt1j9elQ0?authuser=0&hl=fr&rclk=1"
    },
    {
        "place_id": "ChIJtfGlbHYj4xIRDRMdd5uFdYo",
        "name": "Octa",
        "description": null,
        "is_spending_on_ads": false,
        "reviews": 4,
        "website": null,
        "owner": {
            "id": "110378681495476783938",
            "name": "Octa (proprietaire)",
            "link": "https://www.google.com/maps/contrib/110378681495476783938"
        },
        "featured_image": "https://lh5.googleusercontent.com/p/AF1QipPImfmN1DHbzCiUX8PBj8o7GK829rPQVDjXzr7z=w408-h612-k-no",
        "main_category": "Cafe",
        "categories": [
            "Cafe"
        ],
        "rating": 4.8,
        "workday_timing": "04:30-01:00",
        "closed_on": [],
        "phone": null,
        "address": "Octa, Av. de l'Independance, Menzel Bourguiba",
        "review_keywords": [],
        "link": "https://www.google.com/maps/place/Octa/data=!4m7!3m6!1s0x12e323766ca5f1b5:0x8a75859b771d130d!8m2!3d37.1570294!4d9.7838657!16s%2Fg%2F11t1h1h8sx!19sChIJtfGlbHYj4xIRDRMdd5uFdYo?authuser=0&hl=fr&rclk=1"
    },
    {
        "place_id": "ChIJ28TuWYUj4xIR_rCB07emYiQ",
        "name": "Cafe des Pyramides",
        "description": null,
        "is_spending_on_ads": false,
        "reviews": 4,
        "website": null,
        "owner": {
            "id": null,
            "name": "Cafe des Pyramides (proprietaire)",
            "link": null
        },
        "featured_image": "https://lh5.googleusercontent.com/p/AF1QipPJ5yCOP7yMXcCsTiNrxdFXVK47MxvczmWNjk0f=w408-h544-k-no",
        "main_category": "Cafe",
        "categories": [
            "Cafe"
        ],
        "rating": 4,
        "workday_timing": "03:00-23:00",
        "closed_on": [],
        "phone": null,
        "address": "5Q5H+HFH Cafe des Pyramides, Av. de L'independance, Menzel Bourguiba",
        "review_keywords": [],
        "link": "https://www.google.com/maps/place/Caf%C3%A9+des+Pyramides/data=!4m7!3m6!1s0x12e3238559eec4db:0x2462a6b7d381b0fe!8m2!3d37.1589433!4d9.7787383!16s%2Fg%2F1hf9tmhh1!19sChIJ28TuWYUj4xIR_rCB07emYiQ?authuser=0&hl=fr&rclk=1"
    },
    {
        "place_id": "ChIJIxI6Xh0j4xIRwfRSyzZ_qJU",
        "name": "Cafe la pausegout",
        "description": null,
        "is_spending_on_ads": false,
        "reviews": 4,
        "website": "http://www.instagram.com/Lapausegout_t",
        "owner": {
            "id": null,
            "name": "Cafe la pausegout (proprietaire)",
            "link": null
        },
        "featured_image": "https://lh5.googleusercontent.com/p/AF1QipM3PAt0IHLbp5SLzG4QZBouas54nAnCd0zwmz6m=w408-h905-k-no",
        "main_category": "Salon de the",
        "categories": [
            "Salon de the"
        ],
        "rating": 4.5,
        "workday_timing": null,
        "closed_on": [],
        "phone": null,
        "address": "5Q4V+HQ9 Cafe la pausegout, rue Robin, Menzel Bourguiba",
        "review_keywords": [],
        "link": "https://www.google.com/maps/place/Caf%C3%A9+la+pausego%C3%BBt/data=!4m7!3m6!1s0x12e3231d5e3a1223:0x95a87f36cb52f4c1!8m2!3d37.1564162!4d9.7944698!16s%2Fg%2F11h1k97vs9!19sChIJIxI6Xh0j4xIRwfRSyzZ_qJU?authuser=0&hl=fr&rclk=1"
    },
    {
        "place_id": "ChIJnXBpT9oj4xIRKY_iNHeztIY",
        "name": "Trip Chocolat",
        "description": null,
        "is_spending_on_ads": false,
        "reviews": 4,
        "website": null,
        "owner": {
            "id": null,
            "name": "Trip Chocolat (proprietaire)",
            "link": null
        },
        "featured_image": "https://lh5.googleusercontent.com/p/AF1QipP9zA57q_AregAeEaPN2Z_iI5j0S7i8QmfVSpuN=w408-h544-k-no",
        "main_category": "Restaurant",
        "categories": [
            "Restaurant"
        ],
        "rating": 4.5,
        "workday_timing": "08:00-00:00",
        "closed_on": [],
        "phone": null,
        "address": "5Q4R+XFV Trip Chocolat, rue Mirabeau, Menzel Bourguiba",
        "review_keywords": [],
        "link": "https://www.google.com/maps/place/Trip+Chocolat/data=!4m7!3m6!1s0x12e323da4f69709d:0x86b4b37734e28f29!8m2!3d37.1574877!4d9.7911626!16s%2Fg%2F11g4f31641!19sChIJnXBpT9oj4xIRKY_iNHeztIY?authuser=0&hl=fr&rclk=1"
    },
    {
        "place_id": "ChIJ3_AKEpEj4xIRDbSyRpevfMg",
        "name": "Restaurant Chaabene",
        "description": null,
        "is_spending_on_ads": false,
        "reviews": 4,
        "website": null,
        "owner": {
            "id": null,
            "name": "Restaurant Chaabene (proprietaire)",
            "link": null
        },
        "featured_image": "https://lh5.googleusercontent.com/p/AF1QipOswC2mnONeyY1Y-YiS7TRPdOYv--FHpxRJzjMt=w408-h306-k-no",
        "main_category": "Restaurant",
        "categories": [
            "Restaurant"
        ],
        "rating": 4.8,
        "workday_timing": "09:00-23:00",
        "closed_on": [],
        "phone": null,
        "address": "5Q3W+4QX Restaurant Chaabene, blvd Saadi Carnot, Menzel Bourguiba",
        "review_keywords": [],
        "link": "https://www.google.com/maps/place/Restaurant+Chaabene/data=!4m7!3m6!1s0x12e32391120af0df:0xc87caf9746b2b40d!8m2!3d37.1528693!4d9.7969841!16s%2Fg%2F11hz9jf6lb!19sChIJ3_AKEpEj4xIRDbSyRpevfMg?authuser=0&hl=fr&rclk=1"
    },
    {
        "place_id": "ChIJaca5PIUj4xIRwQOdVPTChpE",
        "name": "Cafe",
        "description": null,
        "is_spending_on_ads": false,
        "reviews": 3,
        "website": null,
        "owner": {
            "id": null,
            "name": "Cafe (proprietaire)",
            "link": null
        },
        "featured_image": "https://lh5.googleusercontent.com/p/AF1QipOSOLWZ2YfrCMr0i8SQJwg8h5nYQ7rP49D_u2y_=w426-h240-k-no",
        "main_category": "Cafe",
        "categories": [
            "Cafe"
        ],
        "rating": 4.3,
        "workday_timing": "05:00-23:00",
        "closed_on": [],
        "phone": null,
        "address": "5Q5G+FQX Cafe, Av. de L'independance, Menzel Bourguiba",
        "review_keywords": [],
        "link": "https://www.google.com/maps/place/Caf%C3%A9/data=!4m7!3m6!1s0x12e323853cb9c669:0x9186c2f4549d03c1!8m2!3d37.1587304!4d9.7769791!16s%2Fg%2F11g_fl1f2!19sChIJaca5PIUj4xIRwQOdVPTChpE?authuser=0&hl=fr&rclk=1"
    },
    {
        "place_id": "ChIJXWbs5Ioj4xIRRNH8L5EwwvI",
        "name": "Cafe Ennour",
        "description": null,
        "is_spending_on_ads": false,
        "reviews": 3,
        "website": null,
        "owner": {
            "id": null,
            "name": "Cafe Ennour (proprietaire)",
            "link": null
        },
        "featured_image": "https://lh5.googleusercontent.com/p/AF1QipP8X2qik-yjJX0dhGLR8kkWKl4ggNGL8Ce0jsR8=w408-h306-k-no",
        "main_category": "Cafe",
        "categories": [
            "Cafe"
        ],
        "rating": 5,
        "workday_timing": "08:00-18:00",
        "closed_on": [],
        "phone": "53 519 566",
        "address": "5Q2Q+576 Cafe Ennour, Unnamed Road, Menzel Bourguiba",
        "review_keywords": [],
        "link": "https://www.google.com/maps/place/Caf%C3%A9+Ennour/data=!4m7!3m6!1s0x12e3238ae4ec665d:0xf2c230912ffcd144!8m2!3d37.1504242!4d9.7881447!16s%2Fg%2F11g6_v96lc!19sChIJXWbs5Ioj4xIRRNH8L5EwwvI?authuser=0&hl=fr&rclk=1"
    },
    {
        "place_id": "ChIJVSkkls8j4xIRrqCFROvPdGQ",
        "name": "cafe LE MARIN",
        "description": null,
        "is_spending_on_ads": false,
        "reviews": 3,
        "website": null,
        "owner": {
            "id": "112230304492387591801",
            "name": "cafe LE MARIN (proprietaire)",
            "link": "https://www.google.com/maps/contrib/112230304492387591801"
        },
        "featured_image": "https://lh5.googleusercontent.com/p/AF1QipO5UIuAo_bBj8I0dX8w7-kBzyJtfpBUzoGUz1qr=w408-h280-k-no",
        "main_category": "Cafe",
        "categories": [
            "Cafe"
        ],
        "rating": 5,
        "workday_timing": "04:00-00:00",
        "closed_on": [],
        "phone": "97 303 107",
        "address": "cafe LE MARIN, Menzel Bourguiba 7050",
        "review_keywords": [],
        "link": "https://www.google.com/maps/place/caf%C3%A9+LE+MARIN/data=!4m7!3m6!1s0x12e323cf96242955:0x6474cfeb4485a0ae!8m2!3d37.158478!4d9.7801187!16s%2Fg%2F11vhpf6tkp!19sChIJVSkkls8j4xIRrqCFROvPdGQ?authuser=0&hl=fr&rclk=1"
    },
    {
        "place_id": "ChIJ79XAYgAl4xIRY2kFo2cBNJg",
        "name": "Cafe Hammadi",
        "description": null,
        "is_spending_on_ads": false,
        "reviews": 3,
        "website": null,
        "owner": {
            "id": null,
            "name": "Cafe Hammadi (proprietaire)",
            "link": null
        },
        "featured_image": null,
        "main_category": "Cafe",
        "categories": [
            "Cafe"
        ],
        "rating": 5,
        "workday_timing": "06:00-21:00",
        "closed_on": [],
        "phone": null,
        "address": "4QVV+4RW Cafe Hammadi, Rue El khansa, Menzel Bourguiba",
        "review_keywords": [],
        "link": "https://www.google.com/maps/place/Caf%C3%A9+Hammadi/data=!4m7!3m6!1s0x12e3250062c0d5ef:0x98340167a3056963!8m2!3d37.1428534!4d9.7945777!16s%2Fg%2F11vql_fhs3!19sChIJ79XAYgAl4xIRY2kFo2cBNJg?authuser=0&hl=fr&rclk=1"
    },
    {
        "place_id": "ChIJiZYxn_Qj4xIROdypdpXTMEc",
        "name": "Cafe Brazilia",
        "description": null,
        "is_spending_on_ads": false,
        "reviews": 3,
        "website": null,
        "owner": {
            "id": null,
            "name": "Cafe Brazilia (proprietaire)",
            "link": null
        },
        "featured_image": "https://lh5.googleusercontent.com/p/AF1QipOP9duY3aKeWdI2kZ0hsiLsIbQV5V-arl7vJUcm=w408-h725-k-no",
        "main_category": "Cafe",
        "categories": [
            "Cafe"
        ],
        "rating": 4.3,
        "workday_timing": "Ouvert 24h/24",
        "closed_on": [],
        "phone": null,
        "address": "5Q3R+5MP Cafe Brazilia, Menzel Bourguiba",
        "review_keywords": [],
        "link": "https://www.google.com/maps/place/Caf%C3%A9+Brazilia/data=!4m7!3m6!1s0x12e323f49f319689:0x4730d39576a9dc39!8m2!3d37.1529592!4d9.7916964!16s%2Fg%2F11dymc4zxb!19sChIJiZYxn_Qj4xIROdypdpXTMEc?authuser=0&hl=fr&rclk=1"
    },
    {
        "place_id": "ChIJ_Sz6nXoj4xIRyKlzNJFhZRg",
        "name": "cafe gouider",
        "description": null,
        "is_spending_on_ads": false,
        "reviews": 3,
        "website": null,
        "owner": {
            "id": null,
            "name": "cafe gouider (proprietaire)",
            "link": null
        },
        "featured_image": "https://lh5.googleusercontent.com/p/AF1QipPtX1sHkGw7qjy5Dn8vh42q2l2v5zPLgI_OQvzw=w408-h544-k-no",
        "main_category": "Cafe",
        "categories": [
            "Cafe"
        ],
        "rating": 5,
        "workday_timing": "04:00-01:00",
        "closed_on": [],
        "phone": null,
        "address": "5Q4G+F92 cafe gouider, Menzel Bourguiba",
        "review_keywords": [],
        "link": "https://www.google.com/maps/place/caf%C3%A9+gouider/data=!4m7!3m6!1s0x12e3237a9dfa2cfd:0x186561913473a9c8!8m2!3d37.1561962!4d9.7757774!16s%2Fg%2F11tfm5npwt!19sChIJ_Sz6nXoj4xIRyKlzNJFhZRg?authuser=0&hl=fr&rclk=1"
    },
    {
        "place_id": "ChIJXURN5a0j4xIRC0ZTP-he6Ws",
        "name": "Cafe Khemiri",
        "description": null,
        "is_spending_on_ads": false,
        "reviews": 2,
        "website": null,
        "owner": {
            "id": "117462156828511314384",
            "name": "Cafe Khemiri (proprietaire)",
            "link": "https://www.google.com/maps/contrib/117462156828511314384"
        },
        "featured_image": "https://streetviewpixels-pa.googleapis.com/v1/thumbnail?panoid=djFTuBpTgRqF32PjI2m6RQ&cb_client=search.gws-prod.gps&w=408&h=240&yaw=201.687&pitch=0&thumbfov=100",
        "main_category": "Cafe",
        "categories": [
            "Cafe"
        ],
        "rating": 5,
        "workday_timing": "04:00-00:00",
        "closed_on": [],
        "phone": "53 164 642",
        "address": "Cafe Khemiri, Passage Tinja, Menzel Bourguiba 7032",
        "review_keywords": [],
        "link": "https://www.google.com/maps/place/Caf%C3%A9+Khemiri/data=!4m7!3m6!1s0x12e323ade54d445d:0x6be95ee83f53460b!8m2!3d37.1593034!4d9.7724892!16s%2Fg%2F11vjn82htf!19sChIJXURN5a0j4xIRC0ZTP-he6Ws?authuser=0&hl=fr&rclk=1"
    },
    {
        "place_id": "ChIJuR9V4bAj4xIRjfXW43kXXGQ",
        "name": "Cafe maryouma",
        "description": null,
        "is_spending_on_ads": false,
        "reviews": 2,
        "website": null,
        "owner": {
            "id": null,
            "name": "Cafe maryouma (proprietaire)",
            "link": null
        },
        "featured_image": "https://lh5.googleusercontent.com/p/AF1QipPXjf9cOgbk05rg4rkbClrVa4fCrJtR0nOJkmuY=w426-h240-k-no",
        "main_category": "Cafe",
        "categories": [
            "Cafe"
        ],
        "rating": 4.5,
        "workday_timing": null,
        "closed_on": [],
        "phone": null,
        "address": "Cafe maryouma, 84 Av. de L'independance, Menzel Bourguiba",
        "review_keywords": [],
        "link": "https://www.google.com/maps/place/Cafe+maryouma/data=!4m7!3m6!1s0x12e323b0e1551fb9:0x645c1779e3d6f58d!8m2!3d37.1593071!4d9.7724747!16s%2Fg%2F11kjp3vsm4!19sChIJuR9V4bAj4xIRjfXW43kXXGQ?authuser=0&hl=fr&rclk=1"
    },
    {
        "place_id": "ChIJ2Z_iXCsj4xIRbXJw0r3UHnk",
        "name": "Roti Express",
        "description": null,
        "is_spending_on_ads": false,
        "reviews": 2,
        "website": null,
        "owner": {
            "id": null,
            "name": "Roti Express (proprietaire)",
            "link": null
        },
        "featured_image": "https://streetviewpixels-pa.googleapis.com/v1/thumbnail?panoid=eVvEsNA_FsxBMVSe0w2-3w&cb_client=search.gws-prod.gps&w=408&h=240&yaw=131.64252&pitch=0&thumbfov=100",
        "main_category": "Restaurant de volaille",
        "categories": [
            "Restaurant de volaille"
        ],
        "rating": 5,
        "workday_timing": "Ouvert 24h/24",
        "closed_on": [
            "lundi"
        ],
        "phone": "50 838 485",
        "address": "Roti Express, 56 Av. de L'independance, Menzel Bourguiba",
        "review_keywords": [],
        "link": "https://www.google.com/maps/place/R%C3%B4ti+Express/data=!4m7!3m6!1s0x12e3232b5ce29fd9:0x791ed4bdd270726d!8m2!3d37.1571093!4d9.7840742!16s%2Fg%2F11rsslk0cy!19sChIJ2Z_iXCsj4xIRbXJw0r3UHnk?authuser=0&hl=fr&rclk=1"
    },
    {
        "place_id": "ChIJi0l1eI4j4xIRKaFsY9QJnfs",
        "name": "La Couronne",
        "description": null,
        "is_spending_on_ads": false,
        "reviews": 2,
        "website": null,
        "owner": {
            "id": null,
            "name": "La Couronne (proprietaire)",
            "link": null
        },
        "featured_image": "https://lh5.googleusercontent.com/p/AF1QipN2LqV2eBwJEVveExDUaWzd3iGUD12bm7HDFAU0=w408-h306-k-no",
        "main_category": "Restaurant",
        "categories": [
            "Restaurant"
        ],
        "rating": 4.5,
        "workday_timing": "08:00-23:00",
        "closed_on": [],
        "phone": null,
        "address": "5Q4M+PPX La Couronne, Av. de L'independance, Menzel Bourguiba",
        "review_keywords": [],
        "link": "https://www.google.com/maps/place/La+Couronne/data=!4m7!3m6!1s0x12e3238e7875498b:0xfb9d09d4636ca129!8m2!3d37.1568525!4d9.7843697!16s%2Fg%2F11fxxtghxh!19sChIJi0l1eI4j4xIRKaFsY9QJnfs?authuser=0&hl=fr&rclk=1"
    },
    {
        "place_id": "ChIJ4bkqoloj4xIR2hKCthzDnsk",
        "name": "Cafe Blel",
        "description": null,
        "is_spending_on_ads": false,
        "reviews": 1,
        "website": null,
        "owner": {
            "id": "109497636722783429110",
            "name": "Cafe Blel (proprietaire)",
            "link": "https://www.google.com/maps/contrib/109497636722783429110"
        },
        "featured_image": "https://streetviewpixels-pa.googleapis.com/v1/thumbnail?panoid=45cvTZGveIXH8JG39BnfTg&cb_client=search.gws-prod.gps&w=408&h=240&yaw=63.449104&pitch=0&thumbfov=100",
        "main_category": "Cafe",
        "categories": [
            "Cafe"
        ],
        "rating": 5,
        "workday_timing": null,
        "closed_on": [],
        "phone": null,
        "address": "Cafe Blel, Station Louages - Bizerte MB, Menzel Bourguiba",
        "review_keywords": [],
        "link": "https://www.google.com/maps/place/Caf%C3%A9+Blel/data=!4m7!3m6!1s0x12e3235aa22ab9e1:0xc99ec31cb68212da!8m2!3d37.1559185!4d9.7889999!16s%2Fg%2F11hmz5gm0h!19sChIJ4bkqoloj4xIR2hKCthzDnsk?authuser=0&hl=fr&rclk=1"
    },
    {
        "place_id": "ChIJtWrP_EEj4xIREJtnuVVvmIs",
        "name": "Hollywood stars",
        "description": null,
        "is_spending_on_ads": false,
        "reviews": 1,
        "website": null,
        "owner": {
            "id": null,
            "name": "Hollywood stars (proprietaire)",
            "link": null
        },
        "featured_image": "https://streetviewpixels-pa.googleapis.com/v1/thumbnail?panoid=fpjalwx3Sr2WL3-2Hfsb1g&cb_client=search.gws-prod.gps&w=408&h=240&yaw=52.243355&pitch=0&thumbfov=100",
        "main_category": "Cafe et restaurant de grillades",
        "categories": [
            "Cafe et restaurant de grillades"
        ],
        "rating": 5,
        "workday_timing": "09:00-19:00",
        "closed_on": [
            "dimanche"
        ],
        "phone": "72 470 423",
        "address": "5Q3V+9HM Hollywood stars, rue de Corse, Menzel Bourguiba",
        "review_keywords": [],
        "link": "https://www.google.com/maps/place/Hollywood+stars/data=!4m7!3m6!1s0x12e32341fccf6ab5:0x8b986f55b9679b10!8m2!3d37.1534579!4d9.7939106!16s%2Fg%2F11gy84pdzh!19sChIJtWrP_EEj4xIREJtnuVVvmIs?authuser=0&hl=fr&rclk=1"
    },
    {
        "place_id": "ChIJ_WnX4mcl4xIRXG0sxIAznB0",
        "name": "Cafe el Gasri",
        "description": null,
        "is_spending_on_ads": false,
        "reviews": 1,
        "website": null,
        "owner": {
            "id": null,
            "name": "Cafe el Gasri (proprietaire)",
            "link": null
        },
        "featured_image": null,
        "main_category": "Cafe",
        "categories": [
            "Cafe"
        ],
        "rating": 5,
        "workday_timing": null,
        "closed_on": [],
        "phone": null,
        "address": "4QXM+229 Cafe el Gasri, Rue de la Liberte, Menzel Bourguiba",
        "review_keywords": [],
        "link": "https://www.google.com/maps/place/Caf%C3%A9+el+Gasri/data=!4m7!3m6!1s0x12e32567e2d769fd:0x1d9c3380c42c6d5c!8m2!3d37.1477958!4d9.7823188!16s%2Fg%2F11vj48gqt1!19sChIJ_WnX4mcl4xIRXG0sxIAznB0?authuser=0&hl=fr&rclk=1"
    }
]