[
    {
        "place_id": "ChIJ-5QWU8oSAhMRgnA_jR8bf5I",
        "name": "Monastir",
        "description": null,
        "is_spending_on_ads": false,
        "reviews": 70,
        "website": null,
        "owner": {
            "id": null,
            "name": "Monastir (proprietaire)",
            "link": null
        },
        "featured_image": "https://lh5.googleusercontent.com/p/AF1QipOEk7QEXgZjujarW7dL8HTiFV83ztwKGovVNDZs=w408-h306-k-no",
        "main_category": "Gare",
        "categories": [
            "Gare"
        ],
        "rating": 3.9,
        "workday_timing": null,
        "closed_on": [],
        "phone": null,
        "address": "Monastir",
        "review_keywords": [
            {
                "keyword": "touristes",
                "count": 3
            }
        ],
        "link": "https://www.google.com/maps/place/Monastir/data=!4m7!3m6!1s0x130212ca531694fb:0x927f1b1f8d3f7082!8m2!3d35.7706263!4d10.8252907!16s%2Fm%2F0131k7w1!19sChIJ-5QWU8oSAhMRgnA_jR8bf5I?authuser=0&hl=fr&rclk=1"
    },
    {
        "place_id": "ChIJ2eJ1oMsSAhMR3aZksxdmEkE",
        "name": "Gare Ferroviaire Habib-Bourguiba de Monastir - SNCFT",
        "description": null,
        "is_spending_on_ads": false,
        "reviews": 63,
        "website": "https://www.sncft.com.tn/",
        "owner": {
            "id": null,
            "name": "Gare Ferroviaire Habib-Bourguiba de Monastir - SNCFT (proprietaire)",
            "link": null
        },
        "featured_image": "https://lh5.googleusercontent.com/p/AF1QipNe3XrKvVBpZlc02asbTPftol_myc-_BgoWVGmY=w408-h271-k-no",
        "main_category": "Guichet de gare",
        "categories": [
            "Guichet de gare"
        ],
        "rating": 3.6,
        "workday_timing": "05:00-22:00",
        "closed_on": [],
        "phone": "73 460 755",
        "address": "QRCG+9J7 Gare Ferroviaire Habib-Bourguiba de Monastir - SNCFT, Monastir",
        "review_keywords": [],
        "link": "https://www.google.com/maps/place/Gare+Ferroviaire+Habib-Bourguiba+de+Monastir+-+SNCFT/data=!4m7!3m6!1s0x130212cba075e2d9:0x41126617b364a6dd!8m2!3d35.770921!4d10.8265489!16s%2Fg%2F11fx7t7lv4!19sChIJ2eJ1oMsSAhMR3aZksxdmEkE?authuser=0&hl=fr&rclk=1"
    },
    {
        "place_id": "ChIJt-2sr8sSAhMR9AVdPVbgzF8",
        "name": "Station Louage Monastir-Jammel-Ksar Hellal",
        "description": null,
        "is_spending_on_ads": false,
        "reviews": 31,
        "website": null,
        "owner": {
            "id": null,
            "name": "Station Louage Monastir-Jammel-Ksar Hellal (proprietaire)",
            "link": null
        },
        "featured_image": "https://lh5.googleusercontent.com/p/AF1QipNbSX-Qr6DSSJQ2n_Y8-633HuHD_7OS4tps5woz=w408-h342-k-no",
        "main_category": "Station de taxis",
        "categories": [
            "Station de taxis"
        ],
        "rating": 3.3,
        "workday_timing": null,
        "closed_on": [],
        "phone": null,
        "address": "QRCG+59V Station Louage Monastir-Jammel-Ksar Hellal, Monastir",
        "review_keywords": [],
        "link": "https://www.google.com/maps/place/Station+Louage+Monastir-Jammel-Ksar+Hellal/data=!4m7!3m6!1s0x130212cbafacedb7:0x5fcce0563d5d05f4!8m2!3d35.7704824!4d10.8259314!16s%2Fg%2F1tfdh53f!19sChIJt-2sr8sSAhMR9AVdPVbgzF8?authuser=0&hl=fr&rclk=1"
    },
    {
        "place_id": "ChIJEzxN4ZUMAhMRCb0tR1gMbP8",
        "name": "Station Shell TSA Skanes-Monastir",
        "description": null,
        "is_spending_on_ads": false,
        "reviews": 24,
        "website": null,
        "owner": {
            "id": null,
            "name": "Station Shell TSA Skanes-Monastir (proprietaire)",
            "link": null
        },
        "featured_image": "https://lh5.googleusercontent.com/p/AF1QipOcgwUTGWHsQlMmTbRRMJ6VQnQ-SsAInSWL1aIc=w408-h544-k-no",
        "main_category": "Station-service",
        "categories": [
            "Station-service"
        ],
        "rating": 4.2,
        "workday_timing": "Ouvert 24h/24",
        "closed_on": [],
        "phone": null,
        "address": "QP5G+XRV Station Shell TSA Skanes-Monastir, Dkhila",
        "review_keywords": [],
        "link": "https://www.google.com/maps/place/Station+Shell+TSA+Skanes-Monastir/data=!4m7!3m6!1s0x13020c95e14d3c13:0xff6c0c58472dbd09!8m2!3d35.76!4d10.727044!16s%2Fg%2F11cs011_34!19sChIJEzxN4ZUMAhMRCb0tR1gMbP8?authuser=0&hl=fr&rclk=1"
    },
    {
        "place_id": "ChIJEczVKMsSAhMRSmcUY_ZiUMk",
        "name": "Station STS Monastir",
        "description": null,
        "is_spending_on_ads": false,
        "reviews": 15,
        "website": null,
        "owner": {
            "id": null,
            "name": "Station STS Monastir (proprietaire)",
            "link": null
        },
        "featured_image": "https://lh5.googleusercontent.com/p/AF1QipO8za9dwFfkgMy1sixpRsaRgaLITAXP7Z_Cg7x_=w408-h306-k-no",
        "main_category": "Societe de transport en bus et autocar",
        "categories": [
            "Societe de transport en bus et autocar"
        ],
        "rating": 2.9,
        "workday_timing": null,
        "closed_on": [],
        "phone": "31 384 050",
        "address": "QRFG+786 Station STS Monastir, Monastir",
        "review_keywords": [],
        "link": "https://www.google.com/maps/place/Station+STS+Monastir/data=!4m7!3m6!1s0x130212cb28d5cc11:0xc95062f66314674a!8m2!3d35.7731713!4d10.8257706!16s%2Fg%2F11c75m_2zt!19sChIJEczVKMsSAhMRSmcUY_ZiUMk?authuser=0&hl=fr&rclk=1"
    },
    {
        "place_id": "ChIJ2SWHJ8sSAhMRqCyq8hgMDK4",
        "name": "Gare Routiere de monastir",
        "description": null,
        "is_spending_on_ads": false,
        "reviews": 14,
        "website": null,
        "owner": {
            "id": null,
            "name": "Gare Routiere de monastir (proprietaire)",
            "link": null
        },
        "featured_image": "https://lh5.googleusercontent.com/p/AF1QipPLZm7Hnb3ZHoer2MTbX1oI7N3pN26GM_Rj7cEF=w408-h306-k-no",
        "main_category": "Societe de transport en bus et autocar",
        "categories": [
            "Societe de transport en bus et autocar"
        ],
        "rating": 3.6,
        "workday_timing": null,
        "closed_on": [],
        "phone": null,
        "address": "QRFG+865 Gare Routiere de monastir, Monastir",
        "review_keywords": [],
        "link": "https://www.google.com/maps/place/Gare+Routi%C3%A8re+de+monastir/data=!4m7!3m6!1s0x130212cb278725d9:0xae0c0c18f2aa2ca8!8m2!3d35.7732706!4d10.825621!16s%2Fg%2F11cr_7t30k!19sChIJ2SWHJ8sSAhMRqCyq8hgMDK4?authuser=0&hl=fr&rclk=1"
    },
    {
        "place_id": "ChIJ7TrB3md1AhMRjJtcuir3Z3s",
        "name": "Station de Transport Terrestre",
        "description": null,
        "is_spending_on_ads": false,
        "reviews": 14,
        "website": null,
        "owner": {
            "id": null,
            "name": "Station de Transport Terrestre (proprietaire)",
            "link": null
        },
        "featured_image": "https://lh5.googleusercontent.com/p/AF1QipMh56apuRNVZPBGTns4jS8mRQDW2wQF4924Tr2K=w408-h306-k-no",
        "main_category": "Gare routiere",
        "categories": [
            "Gare routiere"
        ],
        "rating": 3.6,
        "workday_timing": null,
        "closed_on": [],
        "phone": null,
        "address": "Station de Transport Terrestre, Sousse",
        "review_keywords": [],
        "link": "https://www.google.com/maps/place/Station+de+Transport+Terrestre/data=!4m7!3m6!1s0x13027567dec13aed:0x7b67f72aba5c9b8c!8m2!3d35.8143774!4d10.630389!16s%2Fg%2F1tml7lq8!19sChIJ7TrB3md1AhMRjJtcuir3Z3s?authuser=0&hl=fr&rclk=1"
    },
    {
        "place_id": "ChIJUzdkIWcSAhMRxCdJU55AcxM",
        "name": "Frina Station D'autobus",
        "description": null,
        "is_spending_on_ads": false,
        "reviews": 10,
        "website": null,
        "owner": {
            "id": null,
            "name": "Frina Station D'autobus (proprietaire)",
            "link": null
        },
        "featured_image": "https://streetviewpixels-pa.googleapis.com/v1/thumbnail?panoid=4nq2VaUVn4baVaI4pK_tOg&cb_client=search.gws-prod.gps&w=408&h=240&yaw=62.420174&pitch=0&thumbfov=100",
        "main_category": "Compagnie d'autobus",
        "categories": [
            "Compagnie d'autobus"
        ],
        "rating": 3.4,
        "workday_timing": null,
        "closed_on": [],
        "phone": "73 227 170",
        "address": "PRF9+M3G Frina Station D'autobus, Monastir",
        "review_keywords": [],
        "link": "https://www.google.com/maps/place/Frina+Station+D%27autobus/data=!4m7!3m6!1s0x1302126721643753:0x1373409e534927c4!8m2!3d35.7241765!4d10.8176946!16s%2Fg%2F11b77351_z!19sChIJUzdkIWcSAhMRxCdJU55AcxM?authuser=0&hl=fr&rclk=1"
    },
    {
        "place_id": "ChIJK6_UZisRAhMRpUWCCHGUSSw",
        "name": "station louage",
        "description": null,
        "is_spending_on_ads": false,
        "reviews": 10,
        "website": null,
        "owner": {
            "id": null,
            "name": "station louage (proprietaire)",
            "link": null
        },
        "featured_image": "https://lh5.googleusercontent.com/p/AF1QipNFkHU0SwWTvYaAPNNwRXAp8Fv7Tux938It2nc0=w426-h240-k-no",
        "main_category": "Gare routiere",
        "categories": [
            "Gare routiere"
        ],
        "rating": 3.6,
        "workday_timing": null,
        "closed_on": [],
        "phone": null,
        "address": "station louage, Ksar Hellal",
        "review_keywords": [],
        "link": "https://www.google.com/maps/place/station+louage/data=!4m7!3m6!1s0x1302112b66d4af2b:0x2c499471088245a5!8m2!3d35.643526!4d10.8887011!16s%2Fg%2F1thwllrq!19sChIJK6_UZisRAhMRpUWCCHGUSSw?authuser=0&hl=fr&rclk=1"
    },
    {
        "place_id": "ChIJQZmHXyoSAhMReOQQhphSwHE",
        "name": "Station Taxis MONASTIR",
        "description": null,
        "is_spending_on_ads": false,
        "reviews": 9,
        "website": null,
        "owner": {
            "id": null,
            "name": "Station Taxis MONASTIR (proprietaire)",
            "link": null
        },
        "featured_image": "https://lh5.googleusercontent.com/p/AF1QipPbxGkMYFthAMMIa80_nX5L5YndqXP2SnOn6kAj=w408-h306-k-no",
        "main_category": "Station de taxis",
        "categories": [
            "Station de taxis"
        ],
        "rating": 3.8,
        "workday_timing": null,
        "closed_on": [],
        "phone": "26 968 655",
        "address": "MRPR+VX2 Station Taxis MONASTIR, Ksibet El Mediouni",
        "review_keywords": [],
        "link": "https://www.google.com/maps/place/Station+Taxis+MONASTIR/data=!4m7!3m6!1s0x1302122a5f879941:0x71c052988610e478!8m2!3d35.6871346!4d10.8423954!16s%2Fg%2F1td44l3y!19sChIJQZmHXyoSAhMReOQQhphSwHE?authuser=0&hl=fr&rclk=1"
    },
    {
        "place_id": "ChIJ0wxELssSAhMR1qojZug1CKg",
        "name": "Station Car mHT@ lHflt",
        "description": null,
        "is_spending_on_ads": false,
        "reviews": 8,
        "website": null,
        "owner": {
            "id": null,
            "name": "Station Car mHT@ lHflt (proprietaire)",
            "link": null
        },
        "featured_image": "https://lh5.googleusercontent.com/p/AF1QipNHn5F2Y0yhHAMOYTIcHxaT4_ZRyuFbOj95HIEs=w426-h240-k-no",
        "main_category": "Agence de vente de tickets de bus",
        "categories": [
            "Agence de vente de tickets de bus"
        ],
        "rating": 3.3,
        "workday_timing": null,
        "closed_on": [],
        "phone": null,
        "address": "QRFG+7CJ Station Car mHT@ lHflt, Unnamed Road, Monastir",
        "review_keywords": [],
        "link": "https://www.google.com/maps/place/Station+Car+%D9%85%D8%AD%D8%B7%D8%A9+%D8%A7%D9%84%D8%AD%D8%A7%D9%81%D9%84%D8%A7%D8%AA%E2%80%AD/data=!4m7!3m6!1s0x130212cb2e440cd3:0xa80835e86623aad6!8m2!3d35.7732021!4d10.826026!16s%2Fg%2F11fzhd7m0g!19sChIJ0wxELssSAhMR1qojZug1CKg?authuser=0&hl=fr&rclk=1"
    },
    {
        "place_id": "ChIJc6ZpPcr1_RIRYjsKAwWgauU",
        "name": "Station de Bus STS",
        "description": null,
        "is_spending_on_ads": false,
        "reviews": 5,
        "website": null,
        "owner": {
            "id": null,
            "name": "Station de Bus STS (proprietaire)",
            "link": null
        },
        "featured_image": "https://lh5.googleusercontent.com/p/AF1QipNCZWgnzjJ7Fv3786MU2fJR7RbWLRTpaIJFo1PH=w408-h306-k-no",
        "main_category": "Arret de bus",
        "categories": [
            "Arret de bus"
        ],
        "rating": 3.4,
        "workday_timing": null,
        "closed_on": [],
        "phone": null,
        "address": "Station de Bus STS, M'saken",
        "review_keywords": [],
        "link": "https://www.google.com/maps/place/Station+de+Bus+STS/data=!4m7!3m6!1s0x12fdf5ca3d69a673:0xe56aa005030a3b62!8m2!3d35.7334348!4d10.574663!16s%2Fg%2F1tcyp1fd!19sChIJc6ZpPcr1_RIRYjsKAwWgauU?authuser=0&hl=fr&rclk=1"
    },
    {
        "place_id": "ChIJ06-T2coSAhMRjxZD_W8MgEo",
        "name": "Station Taxi Monastir~Sahline",
        "description": null,
        "is_spending_on_ads": false,
        "reviews": 4,
        "website": null,
        "owner": {
            "id": null,
            "name": "Station Taxi Monastir~Sahline (proprietaire)",
            "link": null
        },
        "featured_image": "https://lh5.googleusercontent.com/p/AF1QipPuaHwL4B3kwrDa2gxW2Lp9PnI2UtuQKdDWc7ZC=w408-h306-k-no",
        "main_category": "Station de taxis",
        "categories": [
            "Station de taxis"
        ],
        "rating": 3,
        "workday_timing": null,
        "closed_on": [],
        "phone": "25 349 808",
        "address": "QRFF+5XJ Station Taxi Monastir~Sahline, Monastir",
        "review_keywords": [],
        "link": "https://www.google.com/maps/place/Station+Taxi+Monastir~Sahline/data=!4m7!3m6!1s0x130212cad993afd3:0x4a800c6ffd43168f!8m2!3d35.7729652!4d10.8248927!16s%2Fg%2F11c1tj4vpc!19sChIJ06-T2coSAhMRjxZD_W8MgEo?authuser=0&hl=fr&rclk=1"
    },
    {
        "place_id": "ChIJq6C-76QSAhMRvI7ThWRfxHY",
        "name": "station faculte 2",
        "description": null,
        "is_spending_on_ads": false,
        "reviews": 4,
        "website": null,
        "owner": {
            "id": null,
            "name": "station faculte 2 (proprietaire)",
            "link": null
        },
        "featured_image": "https://lh5.googleusercontent.com/p/AF1QipNX8kK6Q94FFW-_qJkIvEnwGy5Tz1yhchiwRw7m=w408-h544-k-no",
        "main_category": "Compagnie ferroviaire metropolitaine",
        "categories": [
            "Compagnie ferroviaire metropolitaine"
        ],
        "rating": 4,
        "workday_timing": null,
        "closed_on": [],
        "phone": null,
        "address": "QR65+9PM station faculte 2, Monastir",
        "review_keywords": [],
        "link": "https://www.google.com/maps/place/station+faculte+2/data=!4m7!3m6!1s0x130212a4efbea0ab:0x76c45f6485d38ebc!8m2!3d35.7609603!4d10.8092829!16s%2Fg%2F11hbkjnc7f!19sChIJq6C-76QSAhMRvI7ThWRfxHY?authuser=0&hl=fr&rclk=1"
    },
    {
        "place_id": "ChIJteeguooNAhMRsMvnKul6xvA",
        "name": "Monastir Airport Station",
        "description": null,
        "is_spending_on_ads": false,
        "reviews": 3,
        "website": null,
        "owner": {
            "id": null,
            "name": "Monastir Airport Station (proprietaire)",
            "link": null
        },
        "featured_image": "https://lh5.googleusercontent.com/p/AF1QipO8HaT3lTgM_6Shv6toJP3TsFFQC68AJMfwVkLY=w408-h544-k-no",
        "main_category": "Service de transport",
        "categories": [
            "Service de transport"
        ],
        "rating": 3,
        "workday_timing": null,
        "closed_on": [],
        "phone": null,
        "address": "QQ73+3R7 Monastir Airport Station, Monastir",
        "review_keywords": [],
        "link": "https://www.google.com/maps/place/Monastir+Airport+Station/data=!4m7!3m6!1s0x13020d8abaa0e7b5:0xf0c67ae92ae7cbb0!8m2!3d35.7626611!4d10.7545605!16s%2Fg%2F11ty7r4126!19sChIJteeguooNAhMRsMvnKul6xvA?authuser=0&hl=fr&rclk=1"
    },
    {
        "place_id": "ChIJzX1vec8LAhMRRThQj_BPs4I",
        "name": "Station autobus",
        "description": null,
        "is_spending_on_ads": false,
        "reviews": 2,
        "website": null,
        "owner": {
            "id": null,
            "name": "Station autobus (proprietaire)",
            "link": null
        },
        "featured_image": "https://streetviewpixels-pa.googleapis.com/v1/thumbnail?panoid=iH0bVI2lwR9ocv7IXb8iGQ&cb_client=search.gws-prod.gps&w=408&h=240&yaw=277.30228&pitch=0&thumbfov=100",
        "main_category": "Compagnie d'autobus",
        "categories": [
            "Compagnie d'autobus"
        ],
        "rating": 4.5,
        "workday_timing": null,
        "closed_on": [],
        "phone": null,
        "address": "QMFQ+7MP Station autobus, Monastir",
        "review_keywords": [],
        "link": "https://www.google.com/maps/place/Station+autobus/data=!4m7!3m6!1s0x13020bcf796f7dcd:0x82b34ff08f503845!8m2!3d35.7732239!4d10.6891907!16s%2Fg%2F11jnlq0m5s!19sChIJzX1vec8LAhMRRThQj_BPs4I?authuser=0&hl=fr&rclk=1"
    },
    {
        "place_id": "ChIJ8a9Hx2wNAhMRodVAQqvs2kc",
        "name": "Station autobus",
        "description": null,
        "is_spending_on_ads": false,
        "reviews": 2,
        "website": null,
        "owner": {
            "id": null,
            "name": "Station autobus (proprietaire)",
            "link": null
        },
        "featured_image": "https://streetviewpixels-pa.googleapis.com/v1/thumbnail?panoid=ddYFOxSm6P5Ua3PdM7M6UA&cb_client=search.gws-prod.gps&w=408&h=240&yaw=162.66492&pitch=0&thumbfov=100",
        "main_category": "Compagnie d'autobus",
        "categories": [
            "Compagnie d'autobus"
        ],
        "rating": 3,
        "workday_timing": null,
        "closed_on": [],
        "phone": null,
        "address": "QQ62+RWM Station autobus, Monastir",
        "review_keywords": [],
        "link": "https://www.google.com/maps/place/Station+autobus/data=!4m7!3m6!1s0x13020d6cc747aff1:0x47daecab4240d5a1!8m2!3d35.7620786!4d10.7523007!16s%2Fg%2F11jnktty59!19sChIJ8a9Hx2wNAhMRodVAQqvs2kc?authuser=0&hl=fr&rclk=1"
    },
    {
        "place_id": "ChIJOXQvOQULAhMRpJY2Rt_lt-w",
        "name": "Station autobus",
        "description": null,
        "is_spending_on_ads": false,
        "reviews": 2,
        "website": null,
        "owner": {
            "id": null,
            "name": "Station autobus (proprietaire)",
            "link": null
        },
        "featured_image": "https://streetviewpixels-pa.googleapis.com/v1/thumbnail?panoid=kOon9jDhVl4P5lHvj-ArZw&cb_client=search.gws-prod.gps&w=408&h=240&yaw=49.327198&pitch=0&thumbfov=100",
        "main_category": "Compagnie d'autobus",
        "categories": [
            "Compagnie d'autobus"
        ],
        "rating": 5,
        "workday_timing": null,
        "closed_on": [],
        "phone": null,
        "address": "QP35+V2G Station autobus, Sahline",
        "review_keywords": [],
        "link": "https://www.google.com/maps/place/Station+autobus/data=!4m7!3m6!1s0x13020b05392f7439:0xecb7e5df463696a4!8m2!3d35.7546956!4d10.7075665!16s%2Fg%2F11jmx7nx__!19sChIJOXQvOQULAhMRpJY2Rt_lt-w?authuser=0&hl=fr&rclk=1"
    },
    {
        "place_id": "ChIJdb1iLDcWAhMR0aTJgkWL53g",
        "name": "Station STS",
        "description": null,
        "is_spending_on_ads": false,
        "reviews": 2,
        "website": null,
        "owner": {
            "id": null,
            "name": "Station STS (proprietaire)",
            "link": null
        },
        "featured_image": "https://streetviewpixels-pa.googleapis.com/v1/thumbnail?panoid=KrUKFyT40ikYmalEOlyNkA&cb_client=search.gws-prod.gps&w=408&h=240&yaw=269.41736&pitch=0&thumbfov=100",
        "main_category": "Gare routiere",
        "categories": [
            "Gare routiere"
        ],
        "rating": 2,
        "workday_timing": null,
        "closed_on": [],
        "phone": null,
        "address": "Station STS, Tabulbah",
        "review_keywords": [],
        "link": "https://www.google.com/maps/place/Station+STS/data=!4m7!3m6!1s0x130216372c62bd75:0x78e78b4582c9a4d1!8m2!3d35.640107!4d10.9635656!16s%2Fg%2F11bbs2z5jr!19sChIJdb1iLDcWAhMR0aTJgkWL53g?authuser=0&hl=fr&rclk=1"
    },
    {
        "place_id": "ChIJV9GcfipzAhMRI8XIx0hYUTM",
        "name": "Station autobus Skanes - Les Palmiers",
        "description": null,
        "is_spending_on_ads": false,
        "reviews": 1,
        "website": null,
        "owner": {
            "id": null,
            "name": "Station autobus Skanes - Les Palmiers (proprietaire)",
            "link": null
        },
        "featured_image": "https://streetviewpixels-pa.googleapis.com/v1/thumbnail?panoid=EnOgqbIj7Zz6cpbkJBdIng&cb_client=search.gws-prod.gps&w=408&h=240&yaw=235.34697&pitch=0&thumbfov=100",
        "main_category": "Compagnie d'autobus",
        "categories": [
            "Compagnie d'autobus"
        ],
        "rating": 3,
        "workday_timing": null,
        "closed_on": [],
        "phone": null,
        "address": "QQHQ+2XJ Station autobus Skanes - Les Palmiers, Monastir",
        "review_keywords": [],
        "link": "https://www.google.com/maps/place/Station+autobus+Skan%C3%A8s+-+Les+Palmiers/data=!4m7!3m6!1s0x1302732a7e9cd157:0x33515848c7c8c523!8m2!3d35.7775864!4d10.7898886!16s%2Fg%2F11tjzz4y2r!19sChIJV9GcfipzAhMRI8XIx0hYUTM?authuser=0&hl=fr&rclk=1"
    },
    {
        "place_id": "ChIJ6UBJaA8NAhMRKbdTCOAnM1g",
        "name": "Station autobus",
        "description": null,
        "is_spending_on_ads": false,
        "reviews": 1,
        "website": null,
        "owner": {
            "id": null,
            "name": "Station autobus (proprietaire)",
            "link": null
        },
        "featured_image": "https://streetviewpixels-pa.googleapis.com/v1/thumbnail?panoid=5sGH69qMMEO3GDtXC8vyqQ&cb_client=search.gws-prod.gps&w=408&h=240&yaw=40.289978&pitch=0&thumbfov=100",
        "main_category": "Compagnie d'autobus",
        "categories": [
            "Compagnie d'autobus"
        ],
        "rating": 4,
        "workday_timing": null,
        "closed_on": [],
        "phone": null,
        "address": "QP6W+7FV Station autobus, Monastir",
        "review_keywords": [],
        "link": "https://www.google.com/maps/place/Station+autobus/data=!4m7!3m6!1s0x13020d0f684940e9:0x583327e00853b729!8m2!3d35.7607373!4d10.7461682!16s%2Fg%2F11jnft8gzv!19sChIJ6UBJaA8NAhMRKbdTCOAnM1g?authuser=0&hl=fr&rclk=1"
    },
    {
        "place_id": "ChIJZzDJkL8NAhMRm5NhUnKjSFE",
        "name": "Station louage Sahline-Monastir",
        "description": null,
        "is_spending_on_ads": false,
        "reviews": 1,
        "website": null,
        "owner": {
            "id": null,
            "name": "Station louage Sahline-Monastir (proprietaire)",
            "link": null
        },
        "featured_image": "https://streetviewpixels-pa.googleapis.com/v1/thumbnail?panoid=l5C-F6XJG4rtpcgu6C5K1w&cb_client=search.gws-prod.gps&w=408&h=240&yaw=308.9772&pitch=0&thumbfov=100",
        "main_category": "Station de taxis",
        "categories": [
            "Station de taxis"
        ],
        "rating": 4,
        "workday_timing": null,
        "closed_on": [],
        "phone": null,
        "address": "QP26+JPX Station louage Sahline-Monastir, Sahline",
        "review_keywords": [],
        "link": "https://www.google.com/maps/place/Station+louage+Sahline-Monastir/data=!4m7!3m6!1s0x13020dbf90c93067:0x5148a3725261939b!8m2!3d35.7516248!4d10.7118553!16s%2Fg%2F11jmwrs6jy!19sChIJZzDJkL8NAhMRm5NhUnKjSFE?authuser=0&hl=fr&rclk=1"
    },
    {
        "place_id": "ChIJIZGqdAkNAhMR1UyAd8mx16k",
        "name": "Station autobus",
        "description": null,
        "is_spending_on_ads": false,
        "reviews": 1,
        "website": null,
        "owner": {
            "id": null,
            "name": "Station autobus (proprietaire)",
            "link": null
        },
        "featured_image": "https://streetviewpixels-pa.googleapis.com/v1/thumbnail?panoid=urDxlgQwf3s3rgGchd9SXw&cb_client=search.gws-prod.gps&w=408&h=240&yaw=142.53642&pitch=0&thumbfov=100",
        "main_category": "Compagnie d'autobus",
        "categories": [
            "Compagnie d'autobus"
        ],
        "rating": 3,
        "workday_timing": null,
        "closed_on": [],
        "phone": null,
        "address": "QQ97+5W6 Station autobus, Lac de Monastir, Sahline",
        "review_keywords": [],
        "link": "https://www.google.com/maps/place/Station+autobus/data=!4m7!3m6!1s0x13020d0974aa9121:0xa9d7b1c977804cd5!8m2!3d35.7679165!4d10.7647602!16s%2Fg%2F11fwsvzlvm!19sChIJIZGqdAkNAhMR1UyAd8mx16k?authuser=0&hl=fr&rclk=1"
    },
    {
        "place_id": "ChIJtxQKuTcTAhMRbdh0LXMVDyU",
        "name": "Satation de autobus faculte de sciences",
        "description": null,
        "is_spending_on_ads": false,
        "reviews": 1,
        "website": null,
        "owner": {
            "id": null,
            "name": "Satation de autobus faculte de sciences (proprietaire)",
            "link": null
        },
        "featured_image": "https://streetviewpixels-pa.googleapis.com/v1/thumbnail?panoid=1xS1jswbIqoVn-CA0_yZzw&cb_client=search.gws-prod.gps&w=408&h=240&yaw=354.65628&pitch=0&thumbfov=100",
        "main_category": "Station-service",
        "categories": [
            "Station-service"
        ],
        "rating": 4,
        "workday_timing": null,
        "closed_on": [],
        "phone": null,
        "address": "QR74+HH7 Satation de autobus faculte de sciences, Monastir",
        "review_keywords": [],
        "link": "https://www.google.com/maps/place/Satation+de+autobus+facult%C3%A9+de+sciences/data=!4m7!3m6!1s0x13021337b90a14b7:0x250f15732d74d86d!8m2!3d35.7639087!4d10.806423!16s%2Fg%2F11sq_yyztx!19sChIJtxQKuTcTAhMRbdh0LXMVDyU?authuser=0&hl=fr&rclk=1"
    },
    {
        "place_id": "ChIJPYJwNCgTAhMRLbwt-pUHTCU",
        "name": "Train station Hbib Bourgiba",
        "description": null,
        "is_spending_on_ads": false,
        "reviews": 1,
        "website": null,
        "owner": {
            "id": null,
            "name": "Train station Hbib Bourgiba (proprietaire)",
            "link": null
        },
        "featured_image": null,
        "main_category": "Service de transport",
        "categories": [
            "Service de transport"
        ],
        "rating": 5,
        "workday_timing": null,
        "closed_on": [],
        "phone": null,
        "address": "QR76+PG3 Train station Hbib Bourgiba, Monastir",
        "review_keywords": [],
        "link": "https://www.google.com/maps/place/Train+station+Hbib+Bourgiba/data=!4m7!3m6!1s0x130213283470823d:0x254c0795fa2dbc2d!8m2!3d35.7642625!4d10.8112969!16s%2Fg%2F11sjrm0frv!19sChIJPYJwNCgTAhMRLbwt-pUHTCU?authuser=0&hl=fr&rclk=1"
    },
    {
        "place_id": "ChIJZw9vmW4NAhMRZottb8gbgTw",
        "name": "Station autobus",
        "description": null,
        "is_spending_on_ads": false,
        "reviews": 1,
        "website": null,
        "owner": {
            "id": null,
            "name": "Station autobus (proprietaire)",
            "link": null
        },
        "featured_image": "https://streetviewpixels-pa.googleapis.com/v1/thumbnail?panoid=EsGegnSMccbQmA63FBQ39w&cb_client=search.gws-prod.gps&w=408&h=240&yaw=95.341805&pitch=0&thumbfov=100",
        "main_category": "Compagnie d'autobus",
        "categories": [
            "Compagnie d'autobus"
        ],
        "rating": 3,
        "workday_timing": null,
        "closed_on": [],
        "phone": null,
        "address": "PPJH+M6J Station autobus, Sahline",
        "review_keywords": [],
        "link": "https://www.google.com/maps/place/Station+autobus/data=!4m7!3m6!1s0x13020d6e996f0f67:0x3c811bc86f6d8b66!8m2!3d35.7317123!4d10.7280026!16s%2Fg%2F11jnfr_cgf!19sChIJZw9vmW4NAhMRZottb8gbgTw?authuser=0&hl=fr&rclk=1"
    }
]